{"network_type":"cooperation","bridge_nodes":[{"r":1,"n":"Hells Angels Motorcycle Club","c":"United States","x":88,"b":27,"s":49,"d":["Mexican and Colombian Cartel Alliance Network (88)","American Mafia Network (76)","Calabrian 'Ndrangheta Clans Network (42)","Italian Mafia Alliances and Offshoots (28)","Canadian Outlaw Motorcycle Gangs Alliance (23)","Colombian Cartels and International Allies (21)","White Supremacist Prison and Hate Groups (21)","Sureño Prison-Street Gang Alliance (20)","Outlaws MC and Allied Biker Gangs (19)","Bandidos and Allied Motorcycle Clubs (18)","New York Organized Crime Network (14)","Chinese-American and Asian Transnational Gangs (11)","United Nations Gang and Allies (11)","Sydney-based Organized Crime Alliance (11)","Irish-American and Irish Republican Network (9)","New Zealand Gang Alliance Network (9)","Italian-Canadian Mafia and Biker Alliances (8)","Transnational 'Ndrangheta and Mafia Networks (8)","Transnational Asian-Russian Crime Syndicates (8)","Serbian Mafia and Scandinavian Allies (7)","Outlaw Motorcycle Club Alliance (5)","Kinahan-Linked International Crime Network (5)","Canadian Outlaw Motorcycle Club Network (4)","Outlaw Motorcycle Club Network (4)","Rockers MC and Allies Network (4)","Mhallami Mafia Networks in Germany (3)","Finnish Biker Gang Alliance (2)"]},{"r":2,"n":"American Mafia","c":"United States","x":84,"b":22,"s":14,"d":["Mexican and Colombian Cartel Alliance Network (88)","American Mafia Network (76)","Nuova Famiglia Camorra Alliance (53)","Hells Angels and Allied Outlaw Gangs (49)","US Street and Prison Gang Alliances (34)","Sicilian Mafia Corleonesi Alliance Network (34)","Italian Mafia Alliances and Offshoots (28)","Colombian Cartels and International Allies (21)","Second 'Ndrangheta War Alliance (21)","White Supremacist Prison and Hate Groups (21)","Sureño Prison-Street Gang Alliance (20)","Outlaws MC and Allied Biker Gangs (19)","San Luca 'Ndrangheta Clans Alliance (14)","Asian-American Street Gangs and Tongs (12)","Sicilian Mafia and Corsican Allies (11)","Chinese-American and Asian Transnational Gangs (11)","Irish-American and Irish Republican Network (9)","Venezuelan-Mexican Criminal Alliance (9)","Transnational 'Ndrangheta and Mafia Networks (8)","Transnational Asian-Russian Crime Syndicates (8)","LA-Based Ethnic Gang Alliance (3)","Chinatown Gang Alliance Network (3)"]},{"r":3,"n":"'Ndrangheta","c":"Italy","x":83,"b":28,"s":28,"d":["Mexican and Colombian Cartel Alliance Network (88)","American Mafia Network (76)","Nuova Famiglia Camorra Alliance (53)","Hells Angels and Allied Outlaw Gangs (49)","Calabrian 'Ndrangheta Clans Network (42)","Brazilian PCC-Led Criminal Alliance Network (36)","Sicilian Mafia Corleonesi Alliance Network (34)","Canadian Outlaw Motorcycle Gangs Alliance (23)","Secondigliano Camorra Alliance (21)","New York Organized Crime Network (14)","Mancuso-Led 'Ndrangheta Clan Network (12)","Asian-American Street Gangs and Tongs (12)","Sicilian Mafia Alliances Network (12)","Sicilian Mafia and Corsican Allies (11)","Rome-based Mafia and Far-Right Alliance (10)","Ecuadorian-Albanian Drug Trafficking Alliance (9)","Venezuelan-Mexican Criminal Alliance (9)","Haitian-American Gang Alliance Network (9)","Italian-Canadian Mafia and Biker Alliances (8)","Oppido Mamertina 'Ndrangheta Alliance (8)","European Separatist and Leftist Alliances (7)","Bari Mafia Alliance Network (5)","Colombian Caribbean Drug Trafficking Network (5)","Kinahan-Linked International Crime Network (5)","Italian Drug Trafficking Clans (4)","Russian Mafia Power Network (4)","Montenegrin Criminal Clans Alliance (2)","Italian Mafia Clans Cooperation (2)"]},{"r":4,"n":"Sinaloa Cartel","c":"Mexico","x":72,"b":20,"s":88,"d":["Hells Angels and Allied Outlaw Gangs (49)","US Street and Prison Gang Alliances (34)","Italian Mafia Alliances and Offshoots (28)","Colombian Cartels and International Allies (21)","Sureño Prison-Street Gang Alliance (20)","Outlaws MC and Allied Biker Gangs (19)","New York Organized Crime Network (14)","Axis of Resistance and Palestinian Militants (14)","Chinese-American and Asian Transnational Gangs (11)","United Nations Gang and Allies (11)","Sinaloa Cartel Factions and Enforcers (10)","Irish-American and Irish Republican Network (9)","Ecuadorian-Albanian Drug Trafficking Alliance (9)","Venezuelan-Mexican Criminal Alliance (9)","La Mayiza Alliance Network (9)","Transnational Asian-Russian Crime Syndicates (8)","Colombian Caribbean Drug Trafficking Network (5)","Kinahan-Linked International Crime Network (5)","Fukuoka Yakuza Alliance Network (4)","LA-Based Ethnic Gang Alliance (3)"]},{"r":5,"n":"Camorra","c":"Italy","x":52,"b":16,"s":28,"d":["Mexican and Colombian Cartel Alliance Network (88)","Global Jihadist Network and Allies (81)","Sicilian Mafia Corleonesi Alliance Network (34)","Colombian Cartels and International Allies (21)","Reggio Calabria 'Ndrangheta Alliance Network (17)","New York Organized Crime Network (14)","Ndrangheta Core and Allied Clans (12)","Sicilian Mafia and Corsican Allies (11)","Chinese-American and Asian Transnational Gangs (11)","Calabrian 'Ndrangheta Public Works Cartel (11)","Rome-based Mafia and Far-Right Alliance (10)","Venezuelan-Mexican Criminal Alliance (9)","Serbian Mafia and Scandinavian Allies (7)","Kinahan-Linked International Crime Network (5)","Veneto Mafia Network (5)","Melbourne Gangland Alliance Network (4)"]},{"r":6,"n":"Outlaws Motorcycle Club","c":"United States","x":52,"b":10,"s":19,"d":["American Mafia Network (76)","Neo-Nazi Terror Network (26)","Canadian Outlaw Motorcycle Gangs Alliance (23)","White Supremacist Prison and Hate Groups (21)","Bandidos and Allied Motorcycle Clubs (18)","New York Organized Crime Network (14)","New Zealand Outlaw Motorcycle Alliance (8)","Outlaw Motorcycle Club Alliance (5)","Kinahan-Linked International Crime Network (5)","Rockers MC and Allies Network (4)"]},{"r":7,"n":"Sicilian Mafia","c":"Italy","x":48,"b":14,"s":11,"d":["Mexican and Colombian Cartel Alliance Network (88)","American Mafia Network (76)","Nuova Famiglia Camorra Alliance (53)","Sicilian Mafia Corleonesi Alliance Network (34)","Cutro-based 'Ndrangheta Clans Alliance (31)","Italian Mafia Alliances and Offshoots (28)","Platì 'Ndrangheta Clans in Northern Italy (23)","Secondigliano Camorra Alliance (21)","New York Organized Crime Network (14)","Calabrian 'Ndrangheta Public Works Cartel (11)","Rome-based Mafia and Far-Right Alliance (10)","Veneto Mafia Network (5)","Russian Mafia Power Network (4)","Cape Town Gang Alliances (3)"]},{"r":8,"n":"Mexican Mafia","c":"United States","x":44,"b":9,"s":20,"d":["Mexican and Colombian Cartel Alliance Network (88)","American Mafia Network (76)","Hells Angels and Allied Outlaw Gangs (49)","Brazilian PCC-Led Criminal Alliance Network (36)","White Supremacist Prison and Hate Groups (21)","Outlaws MC and Allied Biker Gangs (19)","New York Organized Crime Network (14)","Los Angeles Sureño Street Gangs (8)","LA-Based Ethnic Gang Alliance (3)"]},{"r":9,"n":"'Ndrina Mancuso","c":"Italy","x":43,"b":11,"s":12,"d":["Mexican and Colombian Cartel Alliance Network (88)","Nuova Famiglia Camorra Alliance (53)","Calabrian 'Ndrangheta Clans Network (42)","Cutro-based 'Ndrangheta Clans Alliance (31)","Platì 'Ndrangheta Clans in Northern Italy (23)","Reggio Calabria 'Ndrangheta Alliance Network (17)","Ndrangheta Core and Allied Clans (12)","Vibo Valentia 'Ndrangheta Alliance Network (9)","Oppido Mamertina 'Ndrangheta Alliance (8)","Calabrian 'Ndrangheta Clans Alliance (6)","Colombian Caribbean Drug Trafficking Network (5)"]},{"r":10,"n":"Gambino crime family","c":"United States","x":32,"b":12,"s":76,"d":["Nuova Famiglia Camorra Alliance (53)","Hells Angels and Allied Outlaw Gangs (49)","Calabrian 'Ndrangheta Clans Network (42)","Brazilian PCC-Led Criminal Alliance Network (36)","US Street and Prison Gang Alliances (34)","Sicilian Mafia Corleonesi Alliance Network (34)","Italian Mafia Alliances and Offshoots (28)","White Supremacist Prison and Hate Groups (21)","Sureño Prison-Street Gang Alliance (20)","New York Organized Crime Network (14)","Sicilian Mafia and Corsican Allies (11)","Italian-Canadian Mafia and Biker Alliances (8)"]},{"r":11,"n":"Gulf Cartel","c":"Mexico","x":32,"b":7,"s":88,"d":["Calabrian 'Ndrangheta Clans Network (42)","US Street and Prison Gang Alliances (34)","Italian Mafia Alliances and Offshoots (28)","Colombian Cartels and International Allies (21)","Sureño Prison-Street Gang Alliance (20)","La Mayiza Alliance Network (9)","Texas Prison Gang Alliance (3)"]},{"r":12,"n":"Bandidos Motorcycle Club","c":"United States","x":32,"b":6,"s":18,"d":["Mexican and Colombian Cartel Alliance Network (88)","Hells Angels and Allied Outlaw Gangs (49)","Canadian Outlaw Motorcycle Gangs Alliance (23)","Outlaws MC and Allied Biker Gangs (19)","Sydney-based Organized Crime Alliance (11)","New Zealand Gang Alliance Network (9)"]},{"r":13,"n":"West End Gang","c":"Canada","x":29,"b":7,"s":9,"d":["Mexican and Colombian Cartel Alliance Network (88)","Hells Angels and Allied Outlaw Gangs (49)","Canadian Outlaw Motorcycle Gangs Alliance (23)","Colombian Cartels and International Allies (21)","New York Organized Crime Network (14)","Italian-Canadian Mafia and Biker Alliances (8)","Transnational 'Ndrangheta and Mafia Networks (8)"]},{"r":14,"n":"Banda della Magliana","c":"Italy","x":29,"b":6,"s":10,"d":["Italian Mafia Alliances and Offshoots (28)","Secondigliano Camorra Alliance (21)","Reggio Calabria 'Ndrangheta Alliance Network (17)","San Luca 'Ndrangheta Clans Alliance (14)","Sicilian Mafia and Corsican Allies (11)","Facchineri-Led 'Ndrangheta Alliance (7)"]},{"r":15,"n":"Cali Cartel","c":"Colombia","x":28,"b":7,"s":21,"d":["Mexican and Colombian Cartel Alliance Network (88)","Italian Mafia Alliances and Offshoots (28)","Asian-American Street Gangs and Tongs (12)","Irish-American and Irish Republican Network (9)","Transnational Asian-Russian Crime Syndicates (8)","Italian-Canadian Mafia and Biker Alliances (8)","Colombian Caribbean Drug Trafficking Network (5)"]},{"r":16,"n":"Rizzuto crime family","c":"Canada","x":28,"b":6,"s":8,"d":["American Mafia Network (76)","Hells Angels and Allied Outlaw Gangs (49)","Italian Mafia Alliances and Offshoots (28)","Canadian Outlaw Motorcycle Gangs Alliance (23)","Asian-American Street Gangs and Tongs (12)","Irish-American and Irish Republican Network (9)"]},{"r":17,"n":"'Ndrina De Stefano","c":"Italy","x":27,"b":9,"s":17,"d":["Calabrian 'Ndrangheta Clans Network (42)","Italian Mafia Alliances and Offshoots (28)","Second 'Ndrangheta War Alliance (21)","San Luca 'Ndrangheta Clans Alliance (14)","Mancuso-Led 'Ndrangheta Clan Network (12)","Rome-based Mafia and Far-Right Alliance (10)","Oppido Mamertina 'Ndrangheta Alliance (8)","Calabrian 'Ndrangheta Alliance Network (7)","Italian Mafia Funeral Business Alliance (7)"]},{"r":18,"n":"Cártel de Jalisco Nueva Generación","c":"Mexico","x":26,"b":9,"s":88,"d":["Brazilian PCC-Led Criminal Alliance Network (36)","US Street and Prison Gang Alliances (34)","Italian Mafia Alliances and Offshoots (28)","Sureño Prison-Street Gang Alliance (20)","Sinaloa Cartel Factions and Enforcers (10)","Venezuelan-Mexican Criminal Alliance (9)","Ecuadorian-Albanian Drug Trafficking Alliance (9)","Transnational Asian-Russian Crime Syndicates (8)","Mexico City Cartel Alliance Network (5)"]},{"r":19,"n":"'Ndrina Morabito","c":"Italy","x":26,"b":8,"s":12,"d":["Nuova Famiglia Camorra Alliance (53)","Calabrian 'Ndrangheta Clans Network (42)","Italian Mafia Alliances and Offshoots (28)","San Luca 'Ndrangheta Clans Alliance (14)","Mancuso-Led 'Ndrangheta Clan Network (12)","Calabrian 'Ndrangheta Public Works Cartel (11)","Oppido Mamertina 'Ndrangheta Alliance (8)","Calabrian 'Ndrangheta Alliance Network (7)"]},{"r":20,"n":"Clan dei Casalesi","c":"Italy","x":25,"b":10,"s":53,"d":["American Mafia Network (76)","Calabrian 'Ndrangheta Clans Network (42)","Sicilian Mafia Corleonesi Alliance Network (34)","Italian Mafia Alliances and Offshoots (28)","Secondigliano Camorra Alliance (21)","Mancuso-Led 'Ndrangheta Clan Network (12)","Ndrangheta Core and Allied Clans (12)","Calabrian 'Ndrangheta Clans Alliance (6)","Veneto Mafia Network (5)","Camorra Clan Alliance in Campania (2)"]},{"r":21,"n":"Rock Machine Motorcycle Club","c":"Canada","x":25,"b":6,"s":23,"d":["American Mafia Network (76)","Outlaws MC and Allied Biker Gangs (19)","Bandidos and Allied Motorcycle Clubs (18)","Scandinavian Immigrant Street Gangs (13)","Irish-American and Irish Republican Network (9)","Italian-Canadian Mafia and Biker Alliances (8)"]},{"r":22,"n":"'Ndrina Piromalli","c":"Italy","x":24,"b":12,"s":42,"d":["Nuova Famiglia Camorra Alliance (53)","Italian Mafia Alliances and Offshoots (28)","Second 'Ndrangheta War Alliance (21)","San Luca 'Ndrangheta Clans Alliance (14)","Mancuso-Led 'Ndrangheta Clan Network (12)","Ndrangheta Core and Allied Clans (12)","Rome-based Mafia and Far-Right Alliance (10)","Oppido Mamertina 'Ndrangheta Alliance (8)","Calabrian 'Ndrangheta Alliance Network (7)","Ndrangheta Clans in Calabrian Feuds (6)","Bari Mafia Alliance Network (5)","Ndrangheta Clans in Calabrian Feuds (4)"]},{"r":23,"n":"Los Zetas","c":"Mexico","x":23,"b":8,"s":88,"d":["Calabrian 'Ndrangheta Clans Network (42)","Italian Mafia Alliances and Offshoots (28)","Sureño Prison-Street Gang Alliance (20)","Bandidos and Allied Motorcycle Clubs (18)","Axis of Resistance and Palestinian Militants (14)","Sicilian Mafia and Corsican Allies (11)","La Mayiza Alliance Network (9)","Texas Prison Gang Alliance (3)"]},{"r":24,"n":"Revolutionary Armed Forces of Colombia","c":"Colombia","x":22,"b":8,"s":88,"d":["Calabrian 'Ndrangheta Clans Network (42)","Brazilian PCC-Led Criminal Alliance Network (36)","Axis of Resistance and Palestinian Militants (14)","Mancuso-Led 'Ndrangheta Clan Network (12)","Irish-American and Irish Republican Network (9)","European Separatist and Leftist Alliances (7)","Irish Organized Crime and Dissident Republican Alliance (7)","Puerto Rican Independence Militant Network (3)"]},{"r":25,"n":"Mara Salvatrucha","c":"United States","x":22,"b":4,"s":20,"d":["Mexican and Colombian Cartel Alliance Network (88)","Asian-American Street Gangs and Tongs (12)","Venezuelan-Mexican Criminal Alliance (9)","Bloods Alliance and East Coast Affiliates (7)"]},{"r":26,"n":"Nuova Camorra Organizzata","c":"Italy","x":20,"b":6,"s":28,"d":["Nuova Famiglia Camorra Alliance (53)","Calabrian 'Ndrangheta Clans Network (42)","Colombian Cartels and International Allies (21)","Reggio Calabria 'Ndrangheta Alliance Network (17)","Rome-based Mafia and Far-Right Alliance (10)","Oppido Mamertina 'Ndrangheta Alliance (8)"]},{"r":27,"n":"Clan dei Casamonica","c":"Italy","x":20,"b":5,"s":10,"d":["Nuova Famiglia Camorra Alliance (53)","Calabrian 'Ndrangheta Clans Network (42)","Italian Mafia Alliances and Offshoots (28)","Naples Camorra Alliance Network (15)","Ndrangheta Core and Allied Clans (12)"]},{"r":28,"n":"Crips","c":"United States","x":19,"b":12,"s":34,"d":["Mexican and Colombian Cartel Alliance Network (88)","American Mafia Network (76)","Chicago Folk Nation Street Gangs (22)","Sureño Prison-Street Gang Alliance (20)","New York Organized Crime Network (14)","Asian-American Street Gangs and Tongs (12)","Chinese-American and Asian Transnational Gangs (11)","New Zealand Gang Alliance Network (9)","Haitian-American Gang Alliance Network (9)","Bloods Alliance and East Coast Affiliates (7)","Tongan Crip Gang Alliance Network (4)","Outlaw Motorcycle Club Alliances (3)"]},{"r":29,"n":"Aryan Brotherhood","c":"United States","x":19,"b":6,"s":21,"d":["American Mafia Network (76)","Hells Angels and Allied Outlaw Gangs (49)","Sureño Prison-Street Gang Alliance (20)","New York Organized Crime Network (14)","1960s-70s US Radical Underground (7)","Texas Prison Gang Alliance (3)"]},{"r":30,"n":"Tren de Aragua","c":"Venezuela","x":19,"b":6,"s":9,"d":["Mexican and Colombian Cartel Alliance Network (88)","Brazilian PCC-Led Criminal Alliance Network (36)","Italian Mafia Alliances and Offshoots (28)","Sureño Prison-Street Gang Alliance (20)","New York Organized Crime Network (14)","Ecuadorian-Albanian Drug Trafficking Alliance (9)"]},{"r":31,"n":"Commisso 'ndrina","c":"Italy","x":18,"b":8,"s":42,"d":["Mexican and Colombian Cartel Alliance Network (88)","American Mafia Network (76)","Hells Angels and Allied Outlaw Gangs (49)","Secondigliano Camorra Alliance (21)","Naples Camorra Alliance Network (15)","Calabrian 'Ndrangheta Clan Alliances (11)","Vibo Valentia 'Ndrangheta Alliance Network (9)","Transnational 'Ndrangheta and Mafia Networks (8)"]},{"r":32,"n":"Primeiro Comando da Capital","c":"Brazil","x":18,"b":7,"s":36,"d":["Mexican and Colombian Cartel Alliance Network (88)","Italian Mafia Alliances and Offshoots (28)","Japanese Yakuza Syndicates and Federations (17)","Axis of Resistance and Palestinian Militants (14)","Ecuadorian-Albanian Drug Trafficking Alliance (9)","Venezuelan-Mexican Criminal Alliance (9)","Transnational Asian-Russian Crime Syndicates (8)"]},{"r":33,"n":"Latin Kings","c":"United States","x":18,"b":6,"s":34,"d":["Mexican and Colombian Cartel Alliance Network (88)","American Mafia Network (76)","Hells Angels and Allied Outlaw Gangs (49)","Chicago Folk Nation Street Gangs (22)","Colombian Cartels and International Allies (21)","New York Organized Crime Network (14)"]},{"r":34,"n":"Cartel de Medellín","c":"Colombia","x":18,"b":5,"s":21,"d":["Mexican and Colombian Cartel Alliance Network (88)","Hells Angels and Allied Outlaw Gangs (49)","Italian-Canadian Mafia and Biker Alliances (8)","Latin American Leftist Guerrilla Alliance (5)","Colombian Caribbean Drug Trafficking Network (5)"]},{"r":35,"n":"Secondigliano Alliance","c":"Italy","x":18,"b":4,"s":15,"d":["Calabrian 'Ndrangheta Clans Network (42)","Secondigliano Camorra Alliance (21)","Rome-based Mafia and Far-Right Alliance (10)","Neapolitan Camorra Allied Clans (7)"]},{"r":36,"n":"Bonanno crime family","c":"United States","x":18,"b":3,"s":76,"d":["Sicilian Mafia and Corsican Allies (11)","Italian-Canadian Mafia and Biker Alliances (8)","Transnational 'Ndrangheta and Mafia Networks (8)"]},{"r":37,"n":"Mallardo clan","c":"Italy","x":17,"b":5,"s":21,"d":["Nuova Famiglia Camorra Alliance (53)","Calabrian 'Ndrangheta Clans Network (42)","Sicilian Mafia Corleonesi Alliance Network (34)","Italian Mafia Alliances and Offshoots (28)","Naples Camorra Alliance Network (15)"]},{"r":38,"n":"'Ndrina Pelle","c":"Italy","x":16,"b":7,"s":14,"d":["Sicilian Mafia Corleonesi Alliance Network (34)","Cutro-based 'Ndrangheta Clans Alliance (31)","Italian Mafia Alliances and Offshoots (28)","Platì 'Ndrangheta Clans in Northern Italy (23)","Reggio Calabria 'Ndrangheta Alliance Network (17)","Sicilian Mafia Alliances Network (12)","Vibo Valentia 'Ndrangheta Alliance Network (9)"]},{"r":39,"n":"Corleonesi","c":"Italy","x":16,"b":7,"s":34,"d":["American Mafia Network (76)","Nuova Famiglia Camorra Alliance (53)","Italian Mafia Alliances and Offshoots (28)","Secondigliano Camorra Alliance (21)","San Luca 'Ndrangheta Clans Alliance (14)","Sicilian Mafia and Corsican Allies (11)","Italian-Canadian Mafia and Biker Alliances (8)"]},{"r":40,"n":"Nuova Famiglia","c":"Italy","x":15,"b":7,"s":53,"d":["Calabrian 'Ndrangheta Clans Network (42)","Secondigliano Camorra Alliance (21)","New York Organized Crime Network (14)","Ndrangheta Core and Allied Clans (12)","Sicilian Mafia and Corsican Allies (11)","Camorra Alliance in Sele Plain (5)","Camorra Alliances in Scafati (4)"]},{"r":41,"n":"'Ndrina Pesce","c":"Italy","x":15,"b":6,"s":42,"d":["Mexican and Colombian Cartel Alliance Network (88)","Nuova Famiglia Camorra Alliance (53)","Second 'Ndrangheta War Alliance (21)","Mancuso-Led 'Ndrangheta Clan Network (12)","Gallico-Led 'Ndrangheta Alliance Network (11)","Oppido Mamertina 'Ndrangheta Alliance (8)"]},{"r":42,"n":"Buffalo crime family","c":"United States","x":15,"b":5,"s":76,"d":["Hells Angels and Allied Outlaw Gangs (49)","Calabrian 'Ndrangheta Clans Network (42)","Outlaws MC and Allied Biker Gangs (19)","Sicilian Mafia and Corsican Allies (11)","Transnational 'Ndrangheta and Mafia Networks (8)"]},{"r":43,"n":"Mongols MC","c":"United States","x":14,"b":8,"s":19,"d":["Mexican and Colombian Cartel Alliance Network (88)","American Mafia Network (76)","Hells Angels and Allied Outlaw Gangs (49)","US Street and Prison Gang Alliances (34)","White Supremacist Prison and Hate Groups (21)","Sureño Prison-Street Gang Alliance (20)","1960s-70s US Radical Underground (7)","Bronx Gang Peace Coalition (6)"]},{"r":44,"n":"Catania Mafia family","c":"Italy","x":14,"b":5,"s":34,"d":["Nuova Famiglia Camorra Alliance (53)","Italian Mafia Alliances and Offshoots (28)","Secondigliano Camorra Alliance (21)","San Luca 'Ndrangheta Clans Alliance (14)","Sicilian Mafia Alliances Network (12)"]},{"r":45,"n":"Clan Di Lauro","c":"Italy","x":14,"b":5,"s":21,"d":["Nuova Famiglia Camorra Alliance (53)","Calabrian 'Ndrangheta Clans Network (42)","Italian Mafia Alliances and Offshoots (28)","Naples Camorra Alliance Network (15)","Neapolitan Camorra Allied Clans (7)"]},{"r":46,"n":"Hezbollah","c":"Lebanon","x":14,"b":4,"s":14,"d":["Mexican and Colombian Cartel Alliance Network (88)","Global Jihadist Network and Allies (81)","Brazilian PCC-Led Criminal Alliance Network (36)","Kinahan-Linked International Crime Network (5)"]},{"r":47,"n":"Juárez Cartel","c":"Mexico","x":14,"b":4,"s":88,"d":["Colombian Cartels and International Allies (21)","Sureño Prison-Street Gang Alliance (20)","Sinaloa Cartel Factions and Enforcers (10)","La Mayiza Alliance Network (9)"]},{"r":48,"n":"'Ndrina Alvaro","c":"Italy","x":13,"b":8,"s":42,"d":["Mexican and Colombian Cartel Alliance Network (88)","Second 'Ndrangheta War Alliance (21)","Reggio Calabria 'Ndrangheta Alliance Network (17)","San Luca 'Ndrangheta Clans Alliance (14)","Calabrian 'Ndrangheta Public Works Cartel (11)","Rome-based Mafia and Far-Right Alliance (10)","Vibo Valentia 'Ndrangheta Alliance Network (9)","Transnational 'Ndrangheta and Mafia Networks (8)"]},{"r":49,"n":"Satan's Choice Motorcycle Club","c":"Canada","x":13,"b":7,"s":23,"d":["Hells Angels and Allied Outlaw Gangs (49)","Italian Mafia Alliances and Offshoots (28)","Outlaws MC and Allied Biker Gangs (19)","Bandidos and Allied Motorcycle Clubs (18)","Irish-American and Irish Republican Network (9)","Kinahan-Linked International Crime Network (5)","Canadian Outlaw Motorcycle Club Network (4)"]},{"r":50,"n":"'Ndrina Barbaro","c":"Italy","x":13,"b":6,"s":23,"d":["Calabrian 'Ndrangheta Clans Network (42)","Cutro-based 'Ndrangheta Clans Alliance (31)","Second 'Ndrangheta War Alliance (21)","San Luca 'Ndrangheta Clans Alliance (14)","Mancuso-Led 'Ndrangheta Clan Network (12)","Sicilian Mafia and Corsican Allies (11)"]}]}