{
  "canonical_name": "Guerreros Unidos",
  "aliases": [
    "Cartel Guerreros Unidos",
    "Cártel de los Guerreros Unidos"
  ],
  "description": "Mexican criminal organization operating in Morelos and Guerrero states, founded in 2010 by Cleotilde Toribio Rentería (alias El Tilde) after the fragmentation of the Beltrán Leyva Cartel. Engaged in drug trafficking, homicide, kidnapping, extortion, and other crimes. Notorious for the 2014 disappearance of 43 students in Iguala. Currently active.",
  "country": "Mexico",
  "country_links": [
    {
      "country": "United States",
      "evidence_quote": "su célula en Chicago, a donde dirigían la heroína que procesaban en los estados en mención, fue desmantelada por la DEA a finales de 2014",
      "context": "The organization traffics drugs to the United States, specifically heroin to Chicago."
    }
  ],
  "time_period": "2010-present",
  "is_defunct": false,
  "founded_year": "2010",
  "dissolved_year": null,
  "source_url": "https://es.wikipedia.org/w/index.php?title=Guerreros_Unidos&oldid=171045143",
  "source_file": "es_Guerreros_Unidos"
}