{
  "nodes": [
    {
      "standard_name": "'Ndrangheta",
      "original_text_name": "'ndrangheta",
      "aliases": [
        "Picciotteria"
      ],
      "context": "Traditional organized crime organization based in Calabria, Italy.",
      "time_period": null,
      "source_url": "https://it.wikipedia.org/w/index.php?title=Mafia_in_Italia&oldid=150962377"
    },
    {
      "standard_name": "Cosa Nostra",
      "original_text_name": "Cosa nostra",
      "aliases": [],
      "context": "Traditional organized crime organization based in Sicily, Italy.",
      "time_period": null,
      "source_url": "https://it.wikipedia.org/w/index.php?title=Mafia_in_Italia&oldid=150962377"
    },
    {
      "standard_name": "Camorra",
      "original_text_name": "camorra",
      "aliases": [
        "Bella Società Riformata"
      ],
      "context": "Traditional organized crime organization based in Campania, Italy.",
      "time_period": null,
      "source_url": "https://it.wikipedia.org/w/index.php?title=Mafia_in_Italia&oldid=150962377"
    },
    {
      "standard_name": "Beati Paoli",
      "original_text_name": "Beati Paoli",
      "aliases": [],
      "context": "Ancient sect active in Palermo in the 12th century, possibly linked to mafia origins.",
      "time_period": "XII secolo",
      "source_url": "https://it.wikipedia.org/w/index.php?title=Mafia_in_Italia&oldid=150962377"
    },
    {
      "standard_name": "Garduna",
      "original_text_name": "Garduna",
      "aliases": [],
      "context": "Secret sect from Toledo, Spain, from which three knights allegedly originated mafia organizations.",
      "time_period": "XV secolo",
      "source_url": "https://it.wikipedia.org/w/index.php?title=Mafia_in_Italia&oldid=150962377"
    },
    {
      "standard_name": "Carboneria",
      "original_text_name": "Carboneria",
      "aliases": [],
      "context": "Secret society that influenced the formation of other secret organizations in the Kingdom of the Two Sicilies.",
      "time_period": null,
      "source_url": "https://it.wikipedia.org/w/index.php?title=Mafia_in_Italia&oldid=150962377"
    },
    {
      "standard_name": "'Ndrangheta",
      "original_text_name": "'ndrangheta",
      "aliases": [
        "'ndrine"
      ],
      "context": "Calabrian mafia organization, active in drug trafficking, kidnappings, and other crimes.",
      "time_period": null,
      "source_url": "https://it.wikipedia.org/w/index.php?title=Mafia_in_Italia&oldid=150962377"
    },
    {
      "standard_name": "Cosa Nostra",
      "original_text_name": "Cosa nostra",
      "aliases": [],
      "context": "Sicilian mafia organization, involved in drug trafficking and violent conflicts.",
      "time_period": null,
      "source_url": "https://it.wikipedia.org/w/index.php?title=Mafia_in_Italia&oldid=150962377"
    },
    {
      "standard_name": "Camorra",
      "original_text_name": "camorra",
      "aliases": [
        "clan camorristici"
      ],
      "context": "Neapolitan mafia organization, involved in cigarette smuggling, drug trafficking, and waste disposal.",
      "time_period": null,
      "source_url": "https://it.wikipedia.org/w/index.php?title=Mafia_in_Italia&oldid=150962377"
    },
    {
      "standard_name": "Clan des Marseillais",
      "original_text_name": "clan dei Marsigliesi",
      "aliases": [
        "clan dei marsigliesi"
      ],
      "context": "French criminal group active in Rome and Naples, involved in robberies, cigarette smuggling, drug trafficking, and kidnappings.",
      "time_period": "1964-1976",
      "source_url": "https://it.wikipedia.org/w/index.php?title=Mafia_in_Italia&oldid=150962377"
    },
    {
      "standard_name": "Banda della Magliana",
      "original_text_name": "Banda della Magliana",
      "aliases": [],
      "context": "Roman criminal organization with links to southern mafias, operating in Lazio.",
      "time_period": null,
      "source_url": "https://it.wikipedia.org/w/index.php?title=Mafia_in_Italia&oldid=150962377"
    },
    {
      "standard_name": "Banda della Comasina",
      "original_text_name": "Banda della Comasina",
      "aliases": [],
      "context": "Milanese criminal gang led by Renato Vallanzasca, involved in robberies and kidnappings.",
      "time_period": "1970s",
      "source_url": "https://it.wikipedia.org/w/index.php?title=Mafia_in_Italia&oldid=150962377"
    },
    {
      "standard_name": "Clan dei Catanesi",
      "original_text_name": "clan dei Catanesi",
      "aliases": [],
      "context": "Criminal group operating in Turin and Milan, involved in drug trafficking in agreement with 'Ndrangheta.",
      "time_period": "early 1980s to mid-1980s",
      "source_url": "https://it.wikipedia.org/w/index.php?title=Mafia_in_Italia&oldid=150962377"
    },
    {
      "standard_name": "Mala del Brenta",
      "original_text_name": "Mala del Brenta",
      "aliases": [],
      "context": "Veneto criminal organization led by Felice Maniero, facilitated cooperation between southern mafias and local crime.",
      "time_period": "late 1980s to early 1990s",
      "source_url": "https://it.wikipedia.org/w/index.php?title=Mafia_in_Italia&oldid=150962377"
    },
    {
      "standard_name": "Nuova Camorra Organizzata",
      "original_text_name": "Nuova Camorra Organizzata (NCO)",
      "aliases": [
        "NCO"
      ],
      "context": "Camorra restructuring by Raffaele Cutolo, hierarchical mafia-style organization involved in drug trafficking.",
      "time_period": "mid-1970s",
      "source_url": "https://it.wikipedia.org/w/index.php?title=Mafia_in_Italia&oldid=150962377"
    },
    {
      "standard_name": "Sacra Corona Unita",
      "original_text_name": "Sacra Corona Unita",
      "aliases": [],
      "context": "Apulian mafia organization, considered the most powerful in Puglia, founded by Giuseppe Rogoli.",
      "time_period": null,
      "source_url": "https://it.wikipedia.org/w/index.php?title=Mafia_in_Italia&oldid=150962377"
    },
    {
      "standard_name": "Nuova Camorra Pugliese",
      "original_text_name": "Nuova Camorra Pugliese",
      "aliases": [
        "Società foggiana",
        "Camorra barese"
      ],
      "context": "Apulian mafia group that later split into Società foggiana and Camorra barese.",
      "time_period": null,
      "source_url": "https://it.wikipedia.org/w/index.php?title=Mafia_in_Italia&oldid=150962377"
    },
    {
      "standard_name": "'Ndrangheta",
      "original_text_name": "'ndrangheta",
      "aliases": [],
      "context": "Calabrian mafia, considered the richest and most powerful in Italy, with global reach.",
      "time_period": null,
      "source_url": "https://it.wikipedia.org/w/index.php?title=Mafia_in_Italia&oldid=150962377"
    },
    {
      "standard_name": "Cosa Nostra",
      "original_text_name": "Cosa nostra",
      "aliases": [],
      "context": "Sicilian mafia, structured in families and commissions.",
      "time_period": null,
      "source_url": "https://it.wikipedia.org/w/index.php?title=Mafia_in_Italia&oldid=150962377"
    },
    {
      "standard_name": "Camorra",
      "original_text_name": "camorra",
      "aliases": [],
      "context": "Campanian mafia, fragmented into clans, historically involved in smuggling and drug trafficking.",
      "time_period": null,
      "source_url": "https://it.wikipedia.org/w/index.php?title=Mafia_in_Italia&oldid=150962377"
    },
    {
      "standard_name": "Stidda",
      "original_text_name": "Stidda",
      "aliases": [],
      "context": "Sicilian criminal organization, minor compared to the three main mafias.",
      "time_period": "seconda metà del XX secolo",
      "source_url": "https://it.wikipedia.org/w/index.php?title=Mafia_in_Italia&oldid=150962377"
    },
    {
      "standard_name": "Sacra Corona Unita",
      "original_text_name": "Sacra Corona Unita",
      "aliases": [
        "S.C.U."
      ],
      "context": "Apulian mafia, founded in 1981, with hierarchical structure similar to 'Ndrangheta.",
      "time_period": "1981",
      "source_url": "https://it.wikipedia.org/w/index.php?title=Mafia_in_Italia&oldid=150962377"
    },
    {
      "standard_name": "Società foggiana",
      "original_text_name": "Società foggiana",
      "aliases": [],
      "context": "Criminal organization from Foggia, Apulia, under 'Ndrangheta influence.",
      "time_period": "seconda metà del XX secolo",
      "source_url": "https://it.wikipedia.org/w/index.php?title=Mafia_in_Italia&oldid=150962377"
    },
    {
      "standard_name": "Camorra barese",
      "original_text_name": "Camorra barese",
      "aliases": [],
      "context": "Criminal organization from Bari, Apulia.",
      "time_period": "seconda metà del XX secolo",
      "source_url": "https://it.wikipedia.org/w/index.php?title=Mafia_in_Italia&oldid=150962377"
    },
    {
      "standard_name": "Basilischi",
      "original_text_name": "Basilischi",
      "aliases": [],
      "context": "Criminal organization from Basilicata.",
      "time_period": "seconda metà del XX secolo",
      "source_url": "https://it.wikipedia.org/w/index.php?title=Mafia_in_Italia&oldid=150962377"
    },
    {
      "standard_name": "Mala del Brenta",
      "original_text_name": "Mala del Brenta",
      "aliases": [],
      "context": "Criminal organization from Veneto.",
      "time_period": "seconda metà del XX secolo",
      "source_url": "https://it.wikipedia.org/w/index.php?title=Mafia_in_Italia&oldid=150962377"
    },
    {
      "standard_name": "Banda della Magliana",
      "original_text_name": "Banda della Magliana",
      "aliases": [],
      "context": "Roman criminal organization, now defunct or unknown fate.",
      "time_period": "seconda metà del XX secolo",
      "source_url": "https://it.wikipedia.org/w/index.php?title=Mafia_in_Italia&oldid=150962377"
    },
    {
      "standard_name": "Anonima Sarda",
      "original_text_name": "Anonima Sarda",
      "aliases": [],
      "context": "Sardinian criminal organization, now extinct.",
      "time_period": "seconda metà del XX secolo",
      "source_url": "https://it.wikipedia.org/w/index.php?title=Mafia_in_Italia&oldid=150962377"
    },
    {
      "standard_name": "Casamonica",
      "original_text_name": "Casamonica",
      "aliases": [],
      "context": "Sinti clan based in Rome, filled the void left by Banda della Magliana.",
      "time_period": null,
      "source_url": "https://it.wikipedia.org/w/index.php?title=Mafia_in_Italia&oldid=150962377"
    },
    {
      "standard_name": "Di Silvio",
      "original_text_name": "Di Silvio",
      "aliases": [],
      "context": "Sinti clan based in Rome.",
      "time_period": null,
      "source_url": "https://it.wikipedia.org/w/index.php?title=Mafia_in_Italia&oldid=150962377"
    },
    {
      "standard_name": "Spada",
      "original_text_name": "Spada",
      "aliases": [],
      "context": "Sinti clan based in Rome.",
      "time_period": null,
      "source_url": "https://it.wikipedia.org/w/index.php?title=Mafia_in_Italia&oldid=150962377"
    },
    {
      "standard_name": "Moccia",
      "original_text_name": "Moccia",
      "aliases": [],
      "context": "Camorra clan operating in Rome.",
      "time_period": null,
      "source_url": "https://it.wikipedia.org/w/index.php?title=Mafia_in_Italia&oldid=150962377"
    },
    {
      "standard_name": "Senese",
      "original_text_name": "Senese",
      "aliases": [],
      "context": "Camorra clan operating in Rome.",
      "time_period": null,
      "source_url": "https://it.wikipedia.org/w/index.php?title=Mafia_in_Italia&oldid=150962377"
    },
    {
      "standard_name": "Pagnozzi",
      "original_text_name": "Pagnozzi",
      "aliases": [],
      "context": "Camorra clan operating in Rome.",
      "time_period": null,
      "source_url": "https://it.wikipedia.org/w/index.php?title=Mafia_in_Italia&oldid=150962377"
    },
    {
      "standard_name": "Bonavota",
      "original_text_name": "Bonavota",
      "aliases": [],
      "context": "'Ndrina (Calabrian mafia unit) operating in Rome.",
      "time_period": null,
      "source_url": "https://it.wikipedia.org/w/index.php?title=Mafia_in_Italia&oldid=150962377"
    },
    {
      "standard_name": "Marando",
      "original_text_name": "Marando",
      "aliases": [],
      "context": "'Ndrina (Calabrian mafia unit) operating in Rome.",
      "time_period": null,
      "source_url": "https://it.wikipedia.org/w/index.php?title=Mafia_in_Italia&oldid=150962377"
    },
    {
      "standard_name": "Mafia nigeriana",
      "original_text_name": "mafia nigeriana",
      "aliases": [],
      "context": "Nigerian criminal organizations operating in Italy, in business with Cosa Nostra and Camorra.",
      "time_period": "tra la fine del XX secolo e l'inizio del XXI secolo",
      "source_url": "https://it.wikipedia.org/w/index.php?title=Mafia_in_Italia&oldid=150962377"
    },
    {
      "standard_name": "Mafia albanese",
      "original_text_name": "mafia albanese",
      "aliases": [],
      "context": "Albanian criminal organizations operating in Italy, allied with multiple Italian mafias.",
      "time_period": "tra la fine del XX secolo e l'inizio del XXI secolo",
      "source_url": "https://it.wikipedia.org/w/index.php?title=Mafia_in_Italia&oldid=150962377"
    },
    {
      "standard_name": "Triadi cinesi",
      "original_text_name": "Triadi cinesi",
      "aliases": [],
      "context": "Chinese criminal organizations operating in Italy, with links to Camorra.",
      "time_period": "tra la fine del XX secolo e l'inizio del XXI secolo",
      "source_url": "https://it.wikipedia.org/w/index.php?title=Mafia_in_Italia&oldid=150962377"
    },
    {
      "standard_name": "Mafie russofone",
      "original_text_name": "mafie russofone",
      "aliases": [],
      "context": "Russian-speaking criminal organizations operating in Italy, in business with 'Ndrangheta and Camorra.",
      "time_period": "tra la fine del XX secolo e l'inizio del XXI secolo",
      "source_url": "https://it.wikipedia.org/w/index.php?title=Mafia_in_Italia&oldid=150962377"
    },
    {
      "standard_name": "Nuova Camorra Organizzata",
      "original_text_name": "Nuova Camorra Organizzata",
      "aliases": [
        "N.C.O."
      ],
      "context": "Attempted reunification of Camorra by Raffaele Cutolo in the 1970s, now defunct.",
      "time_period": "anni settanta",
      "source_url": "https://it.wikipedia.org/w/index.php?title=Mafia_in_Italia&oldid=150962377"
    },
    {
      "standard_name": "Clan Mazzarella",
      "original_text_name": "clan Mazzarella",
      "aliases": [],
      "context": "Powerful Camorra clan in Naples metropolitan area.",
      "time_period": null,
      "source_url": "https://it.wikipedia.org/w/index.php?title=Mafia_in_Italia&oldid=150962377"
    },
    {
      "standard_name": "Alleanza di Secondigliano",
      "original_text_name": "Alleanza di Secondigliano",
      "aliases": [],
      "context": "Powerful Camorra alliance in Naples metropolitan area.",
      "time_period": null,
      "source_url": "https://it.wikipedia.org/w/index.php?title=Mafia_in_Italia&oldid=150962377"
    },
    {
      "standard_name": "Clan dei Casalesi",
      "original_text_name": "clan dei Casalesi",
      "aliases": [],
      "context": "Powerful Camorra clan in Caserta and province.",
      "time_period": null,
      "source_url": "https://it.wikipedia.org/w/index.php?title=Mafia_in_Italia&oldid=150962377"
    },
    {
      "standard_name": "'Ndrangheta",
      "original_text_name": "'ndrangheta",
      "aliases": [],
      "context": "Traditional mafia organization in Italy, active since at least the 19th century.",
      "time_period": null,
      "source_url": "https://it.wikipedia.org/w/index.php?title=Mafia_in_Italia&oldid=150962377"
    },
    {
      "standard_name": "Cosa Nostra",
      "original_text_name": "Cosa nostra",
      "aliases": [],
      "context": "Traditional mafia organization in Italy, active since at least the 19th century.",
      "time_period": null,
      "source_url": "https://it.wikipedia.org/w/index.php?title=Mafia_in_Italia&oldid=150962377"
    },
    {
      "standard_name": "Camorra",
      "original_text_name": "camorra",
      "aliases": [],
      "context": "Traditional mafia organization in Italy, active since at least the 19th century.",
      "time_period": null,
      "source_url": "https://it.wikipedia.org/w/index.php?title=Mafia_in_Italia&oldid=150962377"
    },
    {
      "standard_name": "Stidda",
      "original_text_name": "stidda",
      "aliases": [],
      "context": "Italian mafia organization mentioned in the context of mafia presence mapping.",
      "time_period": null,
      "source_url": "https://it.wikipedia.org/w/index.php?title=Mafia_in_Italia&oldid=150962377"
    },
    {
      "standard_name": "Basilischi",
      "original_text_name": "basilischi",
      "aliases": [],
      "context": "Italian mafia organization mentioned in the context of mafia presence mapping.",
      "time_period": null,
      "source_url": "https://it.wikipedia.org/w/index.php?title=Mafia_in_Italia&oldid=150962377"
    }
  ],
  "edges": [
    {
      "source": "'Ndrangheta",
      "target": "Cosa Nostra",
      "evidence_quote": "infatti le organizzazioni di tradizione secolare sono la 'ndrangheta , Cosa nostra , e la camorra",
      "context": "The text lists 'Ndrangheta, Cosa Nostra, and Camorra as traditional organizations, but does not assert a relationship between them.",
      "relationship": "other",
      "time_period": null,
      "source_url": "https://it.wikipedia.org/w/index.php?title=Mafia_in_Italia&oldid=150962377"
    },
    {
      "source": "'Ndrangheta",
      "target": "Camorra",
      "evidence_quote": "infatti le organizzazioni di tradizione secolare sono la 'ndrangheta , Cosa nostra , e la camorra",
      "context": "The text lists 'Ndrangheta, Cosa Nostra, and Camorra as traditional organizations, but does not assert a relationship between them.",
      "relationship": "other",
      "time_period": null,
      "source_url": "https://it.wikipedia.org/w/index.php?title=Mafia_in_Italia&oldid=150962377"
    },
    {
      "source": "Cosa Nostra",
      "target": "Camorra",
      "evidence_quote": "infatti le organizzazioni di tradizione secolare sono la 'ndrangheta , Cosa nostra , e la camorra",
      "context": "The text lists 'Ndrangheta, Cosa Nostra, and Camorra as traditional organizations, but does not assert a relationship between them.",
      "relationship": "other",
      "time_period": null,
      "source_url": "https://it.wikipedia.org/w/index.php?title=Mafia_in_Italia&oldid=150962377"
    },
    {
      "source": "Camorra",
      "target": "Carboneria",
      "evidence_quote": "da cui si formarono altre organizzazioni segrete (come la Carboneria ) con particolari riti, regolamenti e linguaggio iniziatico",
      "context": "The text states that from Masonic lodges other secret organizations like Carboneria formed, but does not assert a direct relationship between Camorra and Carboneria.",
      "relationship": "other",
      "time_period": null,
      "source_url": "https://it.wikipedia.org/w/index.php?title=Mafia_in_Italia&oldid=150962377"
    },
    {
      "source": "Camorra",
      "target": "Cosa Nostra",
      "evidence_quote": "i clan camorristici, in combutta con i mafiosi siciliani, riuscirono a sbaragliare la concorrenza straniera del clan dei marsigliesi",
      "context": "Camorra clans allied with Sicilian mafiosi to defeat the foreign competition of the Clan des Marseillais.",
      "relationship": "cooperation",
      "time_period": null,
      "source_url": "https://it.wikipedia.org/w/index.php?title=Mafia_in_Italia&oldid=150962377"
    },
    {
      "source": "'Ndrangheta",
      "target": "Cosa Nostra",
      "evidence_quote": "le 'ndrine calabresi, in collaborazione con le cosche siciliane, alimentarono lo spaccio di eroina di alcune grandi città del Nord Italia",
      "context": "Calabrian 'ndrine collaborated with Sicilian cosche to fuel heroin trafficking in northern Italian cities.",
      "relationship": "cooperation",
      "time_period": "1980s",
      "source_url": "https://it.wikipedia.org/w/index.php?title=Mafia_in_Italia&oldid=150962377"
    },
    {
      "source": "Camorra",
      "target": "Clan des Marseillais",
      "evidence_quote": "i clan camorristici, in combutta con i mafiosi siciliani, riuscirono a sbaragliare la concorrenza straniera del clan dei marsigliesi",
      "context": "Camorra clans, allied with Sicilian mafiosi, defeated the foreign competition of the Clan des Marseillais.",
      "relationship": "conflict",
      "time_period": null,
      "source_url": "https://it.wikipedia.org/w/index.php?title=Mafia_in_Italia&oldid=150962377"
    },
    {
      "source": "Cosa Nostra",
      "target": "Clan des Marseillais",
      "evidence_quote": "Cosa nostra, sfruttando le direttrici tradizionali del contrabbando di sigarette, rilevò gran parte del traffico di eroina fino ad allora appannaggio esclusivo del clan dei marsigliesi",
      "context": "Cosa Nostra took over the heroin traffic previously controlled exclusively by the Clan des Marseillais.",
      "relationship": "conflict",
      "time_period": "second half of the 1970s",
      "source_url": "https://it.wikipedia.org/w/index.php?title=Mafia_in_Italia&oldid=150962377"
    },
    {
      "source": "Banda della Magliana",
      "target": "Camorra",
      "evidence_quote": "la cosiddetta Banda della Magliana, che ebbe stretti legami con le tre mafie meridionali",
      "context": "Banda della Magliana had close ties with the three southern mafias, including Camorra.",
      "relationship": "cooperation",
      "time_period": null,
      "source_url": "https://it.wikipedia.org/w/index.php?title=Mafia_in_Italia&oldid=150962377"
    },
    {
      "source": "Banda della Magliana",
      "target": "Cosa Nostra",
      "evidence_quote": "la cosiddetta Banda della Magliana, che ebbe stretti legami con le tre mafie meridionali",
      "context": "Banda della Magliana had close ties with the three southern mafias, including Cosa Nostra.",
      "relationship": "cooperation",
      "time_period": null,
      "source_url": "https://it.wikipedia.org/w/index.php?title=Mafia_in_Italia&oldid=150962377"
    },
    {
      "source": "Banda della Magliana",
      "target": "'Ndrangheta",
      "evidence_quote": "la cosiddetta Banda della Magliana, che ebbe stretti legami con le tre mafie meridionali",
      "context": "Banda della Magliana had close ties with the three southern mafias, including 'Ndrangheta.",
      "relationship": "cooperation",
      "time_period": null,
      "source_url": "https://it.wikipedia.org/w/index.php?title=Mafia_in_Italia&oldid=150962377"
    },
    {
      "source": "Clan dei Catanesi",
      "target": "'Ndrangheta",
      "evidence_quote": "il cosiddetto clan dei Catanesi operativo a Torino e Milano, dove si impose con metodi violenti e spregiudicati nel nascente business della droga in accordo con la 'ndrangheta",
      "context": "Clan dei Catanesi operated in agreement with 'Ndrangheta in the drug business.",
      "relationship": "cooperation",
      "time_period": "early 1980s",
      "source_url": "https://it.wikipedia.org/w/index.php?title=Mafia_in_Italia&oldid=150962377"
    },
    {
      "source": "Mala del Brenta",
      "target": "'Ndrangheta",
      "evidence_quote": "favorirono la collaborazione tra le mafie meridionali e la piccola criminalità locale",
      "context": "Mala del Brenta facilitated collaboration between southern mafias, including 'Ndrangheta, and local crime.",
      "relationship": "cooperation",
      "time_period": "late 1980s to early 1990s",
      "source_url": "https://it.wikipedia.org/w/index.php?title=Mafia_in_Italia&oldid=150962377"
    },
    {
      "source": "Mala del Brenta",
      "target": "Camorra",
      "evidence_quote": "favorirono la collaborazione tra le mafie meridionali e la piccola criminalità locale",
      "context": "Mala del Brenta facilitated collaboration between southern mafias, including Camorra, and local crime.",
      "relationship": "cooperation",
      "time_period": "late 1980s to early 1990s",
      "source_url": "https://it.wikipedia.org/w/index.php?title=Mafia_in_Italia&oldid=150962377"
    },
    {
      "source": "Mala del Brenta",
      "target": "Cosa Nostra",
      "evidence_quote": "favorirono la collaborazione tra le mafie meridionali e la piccola criminalità locale",
      "context": "Mala del Brenta facilitated collaboration between southern mafias, including Cosa Nostra, and local crime.",
      "relationship": "cooperation",
      "time_period": "late 1980s to early 1990s",
      "source_url": "https://it.wikipedia.org/w/index.php?title=Mafia_in_Italia&oldid=150962377"
    },
    {
      "source": "Nuova Camorra Organizzata",
      "target": "'Ndrangheta",
      "evidence_quote": "la NCO e la 'ndrangheta, sfruttando le loro conoscenze nel mondo carcerario, promossero la nascita di nuovi gruppi mafiosi in Puglia",
      "context": "NCO and 'Ndrangheta together promoted the birth of new mafia groups in Puglia.",
      "relationship": "cooperation",
      "time_period": "1980s",
      "source_url": "https://it.wikipedia.org/w/index.php?title=Mafia_in_Italia&oldid=150962377"
    },
    {
      "source": "Nuova Camorra Organizzata",
      "target": "Camorra",
      "evidence_quote": "la NCO pretese di imporre il suo controllo su tutte le attività illecite nel napoletano e ciò determinò una guerra",
      "context": "NCO tried to impose control over all illegal activities in the Naples area, leading to a war with other Camorra clans.",
      "relationship": "conflict",
      "time_period": "1977-1983",
      "source_url": "https://it.wikipedia.org/w/index.php?title=Mafia_in_Italia&oldid=150962377"
    },
    {
      "source": "Cosa Nostra",
      "target": "'Ndrangheta",
      "evidence_quote": "Cosa nostra a rivolgersi esclusivamente ad essa e alla criminalità albanese per le forniture dello stupefacente",
      "context": "Cosa Nostra turned exclusively to 'Ndrangheta for drug supplies.",
      "relationship": "cooperation",
      "time_period": "2000s",
      "source_url": "https://it.wikipedia.org/w/index.php?title=Mafia_in_Italia&oldid=150962377"
    },
    {
      "source": "'Ndrangheta",
      "target": "Cosa Nostra",
      "evidence_quote": "le organizzazioni di tradizione secolare sono la 'ndrangheta , Cosa nostra , e la camorra",
      "context": "Listed together as traditional mafias, but no specific relationship stated.",
      "relationship": "other",
      "time_period": null,
      "source_url": "https://it.wikipedia.org/w/index.php?title=Mafia_in_Italia&oldid=150962377"
    },
    {
      "source": "'Ndrangheta",
      "target": "Camorra",
      "evidence_quote": "le organizzazioni di tradizione secolare sono la 'ndrangheta , Cosa nostra , e la camorra",
      "context": "Listed together as traditional mafias, but no specific relationship stated.",
      "relationship": "other",
      "time_period": null,
      "source_url": "https://it.wikipedia.org/w/index.php?title=Mafia_in_Italia&oldid=150962377"
    },
    {
      "source": "Cosa Nostra",
      "target": "Camorra",
      "evidence_quote": "le organizzazioni di tradizione secolare sono la 'ndrangheta , Cosa nostra , e la camorra",
      "context": "Listed together as traditional mafias, but no specific relationship stated.",
      "relationship": "other",
      "time_period": null,
      "source_url": "https://it.wikipedia.org/w/index.php?title=Mafia_in_Italia&oldid=150962377"
    },
    {
      "source": "Mafia nigeriana",
      "target": "Cosa Nostra",
      "evidence_quote": "la mafia nigeriana (in affari con Cosa nostra e Camorra)",
      "context": "Nigerian mafia is in business with Cosa Nostra.",
      "relationship": "cooperation",
      "time_period": "tra la fine del XX secolo e l'inizio del XXI secolo",
      "source_url": "https://it.wikipedia.org/w/index.php?title=Mafia_in_Italia&oldid=150962377"
    },
    {
      "source": "Mafia nigeriana",
      "target": "Camorra",
      "evidence_quote": "la mafia nigeriana (in affari con Cosa nostra e Camorra)",
      "context": "Nigerian mafia is in business with Camorra.",
      "relationship": "cooperation",
      "time_period": "tra la fine del XX secolo e l'inizio del XXI secolo",
      "source_url": "https://it.wikipedia.org/w/index.php?title=Mafia_in_Italia&oldid=150962377"
    },
    {
      "source": "Mafia albanese",
      "target": "Cosa Nostra",
      "evidence_quote": "la mafia albanese (alleata di Cosa nostra, Camorra, 'ndrangheta e Sacra Corona Unita)",
      "context": "Albanian mafia is allied with Cosa Nostra.",
      "relationship": "cooperation",
      "time_period": "tra la fine del XX secolo e l'inizio del XXI secolo",
      "source_url": "https://it.wikipedia.org/w/index.php?title=Mafia_in_Italia&oldid=150962377"
    },
    {
      "source": "Mafia albanese",
      "target": "Camorra",
      "evidence_quote": "la mafia albanese (alleata di Cosa nostra, Camorra, 'ndrangheta e Sacra Corona Unita)",
      "context": "Albanian mafia is allied with Camorra.",
      "relationship": "cooperation",
      "time_period": "tra la fine del XX secolo e l'inizio del XXI secolo",
      "source_url": "https://it.wikipedia.org/w/index.php?title=Mafia_in_Italia&oldid=150962377"
    },
    {
      "source": "Mafia albanese",
      "target": "'Ndrangheta",
      "evidence_quote": "la mafia albanese (alleata di Cosa nostra, Camorra, 'ndrangheta e Sacra Corona Unita)",
      "context": "Albanian mafia is allied with 'Ndrangheta.",
      "relationship": "cooperation",
      "time_period": "tra la fine del XX secolo e l'inizio del XXI secolo",
      "source_url": "https://it.wikipedia.org/w/index.php?title=Mafia_in_Italia&oldid=150962377"
    },
    {
      "source": "Mafia albanese",
      "target": "Sacra Corona Unita",
      "evidence_quote": "la mafia albanese (alleata di Cosa nostra, Camorra, 'ndrangheta e Sacra Corona Unita)",
      "context": "Albanian mafia is allied with Sacra Corona Unita.",
      "relationship": "cooperation",
      "time_period": "tra la fine del XX secolo e l'inizio del XXI secolo",
      "source_url": "https://it.wikipedia.org/w/index.php?title=Mafia_in_Italia&oldid=150962377"
    },
    {
      "source": "Triadi cinesi",
      "target": "Camorra",
      "evidence_quote": "le Triadi cinesi (legami con la Camorra)",
      "context": "Chinese triads have links with Camorra.",
      "relationship": "cooperation",
      "time_period": "tra la fine del XX secolo e l'inizio del XXI secolo",
      "source_url": "https://it.wikipedia.org/w/index.php?title=Mafia_in_Italia&oldid=150962377"
    },
    {
      "source": "Mafie russofone",
      "target": "'Ndrangheta",
      "evidence_quote": "le mafie russofone (in affari con 'Ndrangheta e Camorra)",
      "context": "Russian-speaking mafias are in business with 'Ndrangheta.",
      "relationship": "cooperation",
      "time_period": "tra la fine del XX secolo e l'inizio del XXI secolo",
      "source_url": "https://it.wikipedia.org/w/index.php?title=Mafia_in_Italia&oldid=150962377"
    },
    {
      "source": "Mafie russofone",
      "target": "Camorra",
      "evidence_quote": "le mafie russofone (in affari con 'Ndrangheta e Camorra)",
      "context": "Russian-speaking mafias are in business with Camorra.",
      "relationship": "cooperation",
      "time_period": "tra la fine del XX secolo e l'inizio del XXI secolo",
      "source_url": "https://it.wikipedia.org/w/index.php?title=Mafia_in_Italia&oldid=150962377"
    },
    {
      "source": "'Ndrangheta",
      "target": "Nuova Camorra Organizzata",
      "evidence_quote": "la Nuova Camorra Organizzata (N.C.O.), che si rifaceva alle regole e alle gerarchie della camorra ottocentesca e della 'ndrangheta (alla quale Cutolo era affiliato)",
      "context": "N.C.O. was inspired by 'Ndrangheta's rules and hierarchies, and Cutolo was affiliated with 'Ndrangheta.",
      "relationship": "other",
      "time_period": "anni settanta",
      "source_url": "https://it.wikipedia.org/w/index.php?title=Mafia_in_Italia&oldid=150962377"
    },
    {
      "source": "'Ndrangheta",
      "target": "Sacra Corona Unita",
      "evidence_quote": "La Sacra Corona Unita (S.C.U.) si articola in una serie di doti o gradi , molto simili a quelli della 'ndrangheta , che infatti autorizzò la sua fondazione nel 1981",
      "context": "'Ndrangheta authorized the founding of Sacra Corona Unita in 1981.",
      "relationship": "other",
      "time_period": "1981",
      "source_url": "https://it.wikipedia.org/w/index.php?title=Mafia_in_Italia&oldid=150962377"
    },
    {
      "source": "'Ndrangheta",
      "target": "Società foggiana",
      "evidence_quote": "la più violenta e spregiudicata criminalità foggiana , anch'essa sotto l'influenza della 'ndrangheta",
      "context": "Società foggiana is under the influence of 'Ndrangheta.",
      "relationship": "other",
      "time_period": null,
      "source_url": "https://it.wikipedia.org/w/index.php?title=Mafia_in_Italia&oldid=150962377"
    }
  ],
  "source_url": "https://it.wikipedia.org/w/index.php?title=Mafia_in_Italia&oldid=150962377",
  "source_file": "it_Mafia_in_Italia"
}