{
  "nodes": [
    {
      "standard_name": "Islamic State",
      "original_text_name": "Islamic State",
      "aliases": [
        "IS",
        "ISIL",
        "ISIS",
        "Daesh",
        "Islamic State of Iraq and the Levant",
        "Islamic State of Iraq and Syria"
      ],
      "context": "Transnational Salafi jihadist militant organisation and unrecognised quasi-state, active in Iraq, Syria, and Africa.",
      "time_period": "2014–present",
      "source_url": "https://en.wikipedia.org/w/index.php?title=Islamic_State&oldid=1359049369"
    },
    {
      "standard_name": "Jaish al-Ta'ifa al-Mansurah",
      "original_text_name": "Jaish al-Ta'ifa al-Mansurah",
      "aliases": [],
      "context": "Group founded by Abu Omar al-Baghdadi in 2004, precursor to Islamic State.",
      "time_period": "2004",
      "source_url": "https://en.wikipedia.org/w/index.php?title=Islamic_State&oldid=1359049369"
    },
    {
      "standard_name": "Al-Qaeda",
      "original_text_name": "al-Qaeda",
      "aliases": [],
      "context": "Global jihadist organization; Islamic State affiliated with it in Iraq.",
      "time_period": null,
      "source_url": "https://en.wikipedia.org/w/index.php?title=Islamic_State&oldid=1359049369"
    },
    {
      "standard_name": "Al-Qaeda in Iraq",
      "original_text_name": "al-Qaeda in Iraq",
      "aliases": [],
      "context": "Al-Qaeda's branch in Iraq; Islamic State fought alongside them.",
      "time_period": "2003–2006",
      "source_url": "https://en.wikipedia.org/w/index.php?title=Islamic_State&oldid=1359049369"
    },
    {
      "standard_name": "Boko Haram",
      "original_text_name": "Boko Haram",
      "aliases": [],
      "context": "Jihadist group in Nigeria; influenced by al-Muhajir's writings and later became IS affiliate.",
      "time_period": null,
      "source_url": "https://en.wikipedia.org/w/index.php?title=Islamic_State&oldid=1359049369"
    },
    {
      "standard_name": "Al-Nusra Front",
      "original_text_name": "Al-Nusra Front",
      "aliases": [],
      "context": "Syrian jihadist group; listed as opponent of Islamic State.",
      "time_period": null,
      "source_url": "https://en.wikipedia.org/w/index.php?title=Islamic_State&oldid=1359049369"
    },
    {
      "standard_name": "Hay'at Tahrir al-Sham",
      "original_text_name": "Hay'at Tahrir al-Sham",
      "aliases": [],
      "context": "Syrian Islamist group; listed as opponent of Islamic State.",
      "time_period": null,
      "source_url": "https://en.wikipedia.org/w/index.php?title=Islamic_State&oldid=1359049369"
    },
    {
      "standard_name": "Hamas",
      "original_text_name": "Hamas",
      "aliases": [
        "Al-Qassam Brigades"
      ],
      "context": "Palestinian Sunni group; IS regards them as apostates and opponents.",
      "time_period": null,
      "source_url": "https://en.wikipedia.org/w/index.php?title=Islamic_State&oldid=1359049369"
    },
    {
      "standard_name": "Hezbollah",
      "original_text_name": "Hezbollah",
      "aliases": [],
      "context": "Lebanese Shia militant group; listed as opponent of Islamic State.",
      "time_period": null,
      "source_url": "https://en.wikipedia.org/w/index.php?title=Islamic_State&oldid=1359049369"
    },
    {
      "standard_name": "Houthis",
      "original_text_name": "Houthis",
      "aliases": [],
      "context": "Yemeni Shia group; listed as opponent of Islamic State.",
      "time_period": null,
      "source_url": "https://en.wikipedia.org/w/index.php?title=Islamic_State&oldid=1359049369"
    },
    {
      "standard_name": "Free Syrian Army",
      "original_text_name": "Free Syrian Army",
      "aliases": [],
      "context": "Syrian rebel group; listed as opponent of Islamic State.",
      "time_period": null,
      "source_url": "https://en.wikipedia.org/w/index.php?title=Islamic_State&oldid=1359049369"
    },
    {
      "standard_name": "Syrian Democratic Forces",
      "original_text_name": "Syrian Democratic Forces",
      "aliases": [],
      "context": "Kurdish-led alliance; fought against Islamic State and captured Raqqa.",
      "time_period": null,
      "source_url": "https://en.wikipedia.org/w/index.php?title=Islamic_State&oldid=1359049369"
    },
    {
      "standard_name": "Peshmerga",
      "original_text_name": "Peshmerga",
      "aliases": [],
      "context": "Kurdish military forces; listed as opponent of Islamic State.",
      "time_period": null,
      "source_url": "https://en.wikipedia.org/w/index.php?title=Islamic_State&oldid=1359049369"
    },
    {
      "standard_name": "Popular Mobilization Units",
      "original_text_name": "Popular Mobilization Units",
      "aliases": [],
      "context": "Iraqi Shia paramilitary coalition; listed as opponent of Islamic State.",
      "time_period": null,
      "source_url": "https://en.wikipedia.org/w/index.php?title=Islamic_State&oldid=1359049369"
    },
    {
      "standard_name": "Asa'ib Ahl al-Haq",
      "original_text_name": "Asa'ib Ahl al-Haq",
      "aliases": [],
      "context": "Iraqi Shia militia; listed as opponent of Islamic State.",
      "time_period": null,
      "source_url": "https://en.wikipedia.org/w/index.php?title=Islamic_State&oldid=1359049369"
    },
    {
      "standard_name": "Kata'ib Hezbollah",
      "original_text_name": "Kata'ib Hezbollah",
      "aliases": [],
      "context": "Iraqi Shia militia; listed as opponent of Islamic State.",
      "time_period": null,
      "source_url": "https://en.wikipedia.org/w/index.php?title=Islamic_State&oldid=1359049369"
    },
    {
      "standard_name": "Harakat Hezbollah al-Nujaba",
      "original_text_name": "Harakat Hezbollah al-Nujaba",
      "aliases": [],
      "context": "Iraqi Shia militia; listed as opponent of Islamic State.",
      "time_period": null,
      "source_url": "https://en.wikipedia.org/w/index.php?title=Islamic_State&oldid=1359049369"
    },
    {
      "standard_name": "Kata'ib Sayyid al-Shuhada",
      "original_text_name": "Kata'ib Sayyid al-Shuhada",
      "aliases": [],
      "context": "Iraqi Shia militia; listed as opponent of Islamic State.",
      "time_period": null,
      "source_url": "https://en.wikipedia.org/w/index.php?title=Islamic_State&oldid=1359049369"
    },
    {
      "standard_name": "Badr Organization",
      "original_text_name": "Badr Organization",
      "aliases": [],
      "context": "Iraqi Shia political and military group; listed as opponent of Islamic State.",
      "time_period": null,
      "source_url": "https://en.wikipedia.org/w/index.php?title=Islamic_State&oldid=1359049369"
    },
    {
      "standard_name": "Ahrar al-Sham",
      "original_text_name": "Ahrar al-Sham",
      "aliases": [],
      "context": "Syrian Islamist rebel group; listed as opponent of Islamic State.",
      "time_period": null,
      "source_url": "https://en.wikipedia.org/w/index.php?title=Islamic_State&oldid=1359049369"
    },
    {
      "standard_name": "Army of Conquest",
      "original_text_name": "Army of Conquest",
      "aliases": [],
      "context": "Syrian rebel alliance; listed as opponent of Islamic State.",
      "time_period": null,
      "source_url": "https://en.wikipedia.org/w/index.php?title=Islamic_State&oldid=1359049369"
    },
    {
      "standard_name": "Islamic Front",
      "original_text_name": "Islamic Front",
      "aliases": [],
      "context": "Syrian rebel coalition; listed as opponent of Islamic State.",
      "time_period": null,
      "source_url": "https://en.wikipedia.org/w/index.php?title=Islamic_State&oldid=1359049369"
    },
    {
      "standard_name": "Ajnad al-Sham Islamic Union",
      "original_text_name": "Ajnad al-Sham Islamic Union",
      "aliases": [],
      "context": "Syrian Islamist group; listed as opponent of Islamic State.",
      "time_period": null,
      "source_url": "https://en.wikipedia.org/w/index.php?title=Islamic_State&oldid=1359049369"
    },
    {
      "standard_name": "Ba'ath Brigades",
      "original_text_name": "Ba'ath Brigades",
      "aliases": [],
      "context": "Syrian pro-government militia; listed as opponent of Islamic State.",
      "time_period": null,
      "source_url": "https://en.wikipedia.org/w/index.php?title=Islamic_State&oldid=1359049369"
    },
    {
      "standard_name": "Syrian National Army",
      "original_text_name": "Syrian National Army",
      "aliases": [],
      "context": "Turkish-backed Syrian rebel coalition; listed as opponent of Islamic State.",
      "time_period": null,
      "source_url": "https://en.wikipedia.org/w/index.php?title=Islamic_State&oldid=1359049369"
    },
    {
      "standard_name": "Nineveh Plain Protection Units",
      "original_text_name": "Nineveh Plain Protection Units",
      "aliases": [],
      "context": "Assyrian Christian militia; listed as opponent of Islamic State.",
      "time_period": null,
      "source_url": "https://en.wikipedia.org/w/index.php?title=Islamic_State&oldid=1359049369"
    },
    {
      "standard_name": "National Defence Forces",
      "original_text_name": "National Defence Forces",
      "aliases": [],
      "context": "Syrian pro-government militia; listed as opponent of Islamic State.",
      "time_period": null,
      "source_url": "https://en.wikipedia.org/w/index.php?title=Islamic_State&oldid=1359049369"
    },
    {
      "standard_name": "Kurdistan Communities Union",
      "original_text_name": "Kurdistan Communities Union",
      "aliases": [],
      "context": "Kurdish political and militant group; listed as opponent of Islamic State.",
      "time_period": null,
      "source_url": "https://en.wikipedia.org/w/index.php?title=Islamic_State&oldid=1359049369"
    },
    {
      "standard_name": "Libya Shield Force",
      "original_text_name": "Libya Shield Force",
      "aliases": [],
      "context": "Libyan militia coalition; listed as opponent of Islamic State.",
      "time_period": null,
      "source_url": "https://en.wikipedia.org/w/index.php?title=Islamic_State&oldid=1359049369"
    },
    {
      "standard_name": "Shura Council of Mujahideen in Derna",
      "original_text_name": "Shura Council of Mujahideen in Derna",
      "aliases": [],
      "context": "Libyan jihadist coalition; listed as opponent of Islamic State.",
      "time_period": null,
      "source_url": "https://en.wikipedia.org/w/index.php?title=Islamic_State&oldid=1359049369"
    },
    {
      "standard_name": "Liwa Assad Allah al-Ghalib fi al-Iraq wa al-Sham",
      "original_text_name": "Liwa Assad Allah al-Ghalib fi al-Iraq wa al-Sham",
      "aliases": [],
      "context": "Iraqi Shia militia; listed as opponent of Islamic State.",
      "time_period": null,
      "source_url": "https://en.wikipedia.org/w/index.php?title=Islamic_State&oldid=1359049369"
    },
    {
      "standard_name": "Jaysh al-Mu'ammal",
      "original_text_name": "Jaysh al-Mu'ammal",
      "aliases": [],
      "context": "Iraqi Shia militia; listed as opponent of Islamic State.",
      "time_period": null,
      "source_url": "https://en.wikipedia.org/w/index.php?title=Islamic_State&oldid=1359049369"
    },
    {
      "standard_name": "Liwa Fatemiyoun",
      "original_text_name": "Liwa Fatemiyoun",
      "aliases": [],
      "context": "Afghan Shia militia fighting in Syria; listed as opponent of Islamic State.",
      "time_period": null,
      "source_url": "https://en.wikipedia.org/w/index.php?title=Islamic_State&oldid=1359049369"
    },
    {
      "standard_name": "Liwa Zainebiyoun",
      "original_text_name": "Liwa Zainebiyoun",
      "aliases": [],
      "context": "Pakistani Shia militia fighting in Syria; listed as opponent of Islamic State.",
      "time_period": null,
      "source_url": "https://en.wikipedia.org/w/index.php?title=Islamic_State&oldid=1359049369"
    },
    {
      "standard_name": "Husayniyun",
      "original_text_name": "Husayniyun/Hüseynçilər",
      "aliases": [
        "Hüseynçilər"
      ],
      "context": "Azerbaijani Shia militia; listed as opponent of Islamic State.",
      "time_period": null,
      "source_url": "https://en.wikipedia.org/w/index.php?title=Islamic_State&oldid=1359049369"
    },
    {
      "standard_name": "Army of the Men of the Naqshbandi Order",
      "original_text_name": "Army of the Men of the Naqshbandi Order",
      "aliases": [],
      "context": "Iraqi Sufi insurgent group; listed as ally of Islamic State (2014–2015).",
      "time_period": "2014–2015",
      "source_url": "https://en.wikipedia.org/w/index.php?title=Islamic_State&oldid=1359049369"
    },
    {
      "standard_name": "General Military Council for Iraqi Revolutionaries",
      "original_text_name": "General Military Council for Iraqi Revolutionaries",
      "aliases": [],
      "context": "Iraqi Sunni insurgent coalition; listed as ally of Islamic State (2014).",
      "time_period": "2014",
      "source_url": "https://en.wikipedia.org/w/index.php?title=Islamic_State&oldid=1359049369"
    },
    {
      "standard_name": "Islamic State",
      "original_text_name": "Islamic State",
      "aliases": [
        "IS",
        "ISIL",
        "ISIS",
        "Daesh",
        "Islamic State of Iraq and the Levant",
        "Islamic State of Iraq and Syria"
      ],
      "context": "Transnational Salafi jihadist militant organisation and unrecognised quasi-state that controlled territory in Iraq and Syria from 2013 to 2019.",
      "time_period": "2004-present",
      "source_url": "https://en.wikipedia.org/w/index.php?title=Islamic_State&oldid=1359049369"
    },
    {
      "standard_name": "Jaish al-Ta'ifa al-Mansurah",
      "original_text_name": "Jaish al-Ta'ifa al-Mansurah",
      "aliases": [],
      "context": "Group founded by Abu Omar al-Baghdadi in 2004, precursor to the Islamic State.",
      "time_period": "2004",
      "source_url": "https://en.wikipedia.org/w/index.php?title=Islamic_State&oldid=1359049369"
    },
    {
      "standard_name": "Al-Qaeda",
      "original_text_name": "al-Qaeda",
      "aliases": [],
      "context": "Militant Islamist organization; the Islamic State (as Islamic State of Iraq) affiliated with it and fought alongside it during the Iraqi insurgency.",
      "time_period": null,
      "source_url": "https://en.wikipedia.org/w/index.php?title=Islamic_State&oldid=1359049369"
    },
    {
      "standard_name": "Tahrir al-Sham",
      "original_text_name": "Tahrir al-Sham",
      "aliases": [
        "HTS"
      ],
      "context": "Syrian militant group; involved in a shootout that killed an IS leader.",
      "time_period": null,
      "source_url": "https://en.wikipedia.org/w/index.php?title=Islamic_State&oldid=1359049369"
    },
    {
      "standard_name": "Islamic State",
      "original_text_name": "Islamic State",
      "aliases": [
        "IS",
        "ISIL",
        "ISIS",
        "Daesh",
        "Islamic State of Iraq and the Levant",
        "Islamic State of Iraq and Syria"
      ],
      "context": "Transnational Salafi jihadist militant organisation and unrecognised quasi-state, active in Iraq, Syria, and globally.",
      "time_period": "1999-present",
      "source_url": "https://en.wikipedia.org/w/index.php?title=Islamic_State&oldid=1359049369"
    },
    {
      "standard_name": "Al-Qaeda",
      "original_text_name": "Al Qaeda",
      "aliases": [
        "al-Qaeda"
      ],
      "context": "Jihadist organisation that provided financial support to JTJ (precursor to IS).",
      "time_period": null,
      "source_url": "https://en.wikipedia.org/w/index.php?title=Islamic_State&oldid=1359049369"
    },
    {
      "standard_name": "Jaish al-Ta'ifa al-Mansurah",
      "original_text_name": "Jaish al-Ta'ifa al-Mansurah",
      "aliases": [],
      "context": "Originating organisation founded by Abu Omar al-Baghdadi in 2004, precursor to Islamic State.",
      "time_period": "2004",
      "source_url": "https://en.wikipedia.org/w/index.php?title=Islamic_State&oldid=1359049369"
    },
    {
      "standard_name": "Al-Qaeda in Iraq",
      "original_text_name": "al-Qaeda in Iraq",
      "aliases": [],
      "context": "Affiliate of al-Qaeda that the Islamic State of Iraq fought alongside during the Iraqi insurgency.",
      "time_period": "2003-2006",
      "source_url": "https://en.wikipedia.org/w/index.php?title=Islamic_State&oldid=1359049369"
    },
    {
      "standard_name": "Al-Khansaa Brigade",
      "original_text_name": "Al-Khansaa Brigade",
      "aliases": [],
      "context": "All-female media wing of Islamic State.",
      "time_period": null,
      "source_url": "https://en.wikipedia.org/w/index.php?title=Islamic_State&oldid=1359049369"
    },
    {
      "standard_name": "Islamic State – Central Africa Province",
      "original_text_name": "Islamic State – Central Africa Province",
      "aliases": [
        "IS-CAP"
      ],
      "context": "IS affiliate operating in Democratic Republic of the Congo and Uganda.",
      "time_period": "2018-present",
      "source_url": "https://en.wikipedia.org/w/index.php?title=Islamic_State&oldid=1359049369"
    },
    {
      "standard_name": "Allied Democratic Forces",
      "original_text_name": "Allied Democratic Forces",
      "aliases": [
        "ADF"
      ],
      "context": "Ugandan Islamist group from which IS-CAP emerged.",
      "time_period": null,
      "source_url": "https://en.wikipedia.org/w/index.php?title=Islamic_State&oldid=1359049369"
    },
    {
      "standard_name": "Islamic State – Mozambique Province",
      "original_text_name": "Islamic State – Mozambique Province",
      "aliases": [
        "ISMP"
      ],
      "context": "IS affiliate active in Mozambique's Cabo Delgado province, formerly part of IS-CAP.",
      "time_period": "2022-present",
      "source_url": "https://en.wikipedia.org/w/index.php?title=Islamic_State&oldid=1359049369"
    },
    {
      "standard_name": "Al-Shabaab (Mozambique)",
      "original_text_name": "Al-Shabaab",
      "aliases": [],
      "context": "Mozambican Islamist group from which ISMP emerged.",
      "time_period": null,
      "source_url": "https://en.wikipedia.org/w/index.php?title=Islamic_State&oldid=1359049369"
    },
    {
      "standard_name": "Islamic State – Sahel Province",
      "original_text_name": "Islamic State – Sahel Province",
      "aliases": [
        "ISSP",
        "Islamic State in the Greater Sahara",
        "IS-GS"
      ],
      "context": "IS affiliate operating in Mali, Niger, and Burkina Faso.",
      "time_period": "2015-present",
      "source_url": "https://en.wikipedia.org/w/index.php?title=Islamic_State&oldid=1359049369"
    },
    {
      "standard_name": "Islamic State – West Africa Province",
      "original_text_name": "Islamic State – West Africa Province",
      "aliases": [
        "ISWAP"
      ],
      "context": "IS affiliate active in Chad Basin, emerged from split with Boko Haram.",
      "time_period": "2015-present",
      "source_url": "https://en.wikipedia.org/w/index.php?title=Islamic_State&oldid=1359049369"
    },
    {
      "standard_name": "Boko Haram",
      "original_text_name": "Boko Haram",
      "aliases": [],
      "context": "Islamist group from which ISWAP split in 2015.",
      "time_period": null,
      "source_url": "https://en.wikipedia.org/w/index.php?title=Islamic_State&oldid=1359049369"
    },
    {
      "standard_name": "Islamic State – Somalia Province",
      "original_text_name": "Islamic State – Somalia Province",
      "aliases": [
        "ISSP"
      ],
      "context": "IS affiliate operating in Puntland, Somalia, formed by defectors from Al-Shabaab.",
      "time_period": "2015-present",
      "source_url": "https://en.wikipedia.org/w/index.php?title=Islamic_State&oldid=1359049369"
    },
    {
      "standard_name": "Al-Shabaab (Somalia)",
      "original_text_name": "Al-Shabaab",
      "aliases": [],
      "context": "Somali Islamist group from which elements defected to form IS Somalia Province.",
      "time_period": null,
      "source_url": "https://en.wikipedia.org/w/index.php?title=Islamic_State&oldid=1359049369"
    },
    {
      "standard_name": "Islamic State – Azerbaijan Province",
      "original_text_name": "Islamic State – Azerbaijan Province",
      "aliases": [
        "IS-AP"
      ],
      "context": "IS affiliate in Azerbaijan, emerged from recruits of IS-CP and ISIS-K.",
      "time_period": "2019-present",
      "source_url": "https://en.wikipedia.org/w/index.php?title=Islamic_State&oldid=1359049369"
    },
    {
      "standard_name": "Islamic State – Caucasus Province",
      "original_text_name": "Islamic State – Caucasus Province",
      "aliases": [
        "IS-CP"
      ],
      "context": "IS affiliate active in North Caucasus region of Russia.",
      "time_period": "2015-present",
      "source_url": "https://en.wikipedia.org/w/index.php?title=Islamic_State&oldid=1359049369"
    },
    {
      "standard_name": "Islamic State – Khorasan Province",
      "original_text_name": "Islamic State – Khorasan Province",
      "aliases": [
        "ISIS-K"
      ],
      "context": "IS affiliate operating in Central and South Asia.",
      "time_period": "2015-present",
      "source_url": "https://en.wikipedia.org/w/index.php?title=Islamic_State&oldid=1359049369"
    },
    {
      "standard_name": "Islamic State – Bengal Province",
      "original_text_name": "Islamic State – Bengal Province",
      "aliases": [
        "IS-BP"
      ],
      "context": "IS affiliate in Bangladesh, offshoot of Jamaat-ul-Mujahideen Bangladesh.",
      "time_period": "2015-present",
      "source_url": "https://en.wikipedia.org/w/index.php?title=Islamic_State&oldid=1359049369"
    },
    {
      "standard_name": "Jamaat-ul-Mujahideen Bangladesh",
      "original_text_name": "Jamaat-ul-Mujahideen Bangladesh",
      "aliases": [
        "JMB"
      ],
      "context": "Al-Qaeda affiliated group from which IS-BP is an offshoot.",
      "time_period": null,
      "source_url": "https://en.wikipedia.org/w/index.php?title=Islamic_State&oldid=1359049369"
    },
    {
      "standard_name": "Islamic State – Hind Province",
      "original_text_name": "Islamic State – Hind Province",
      "aliases": [
        "ISHP"
      ],
      "context": "Indian branch of IS operating in Jammu and Kashmir.",
      "time_period": "2019-present",
      "source_url": "https://en.wikipedia.org/w/index.php?title=Islamic_State&oldid=1359049369"
    },
    {
      "standard_name": "Islamic State – Pakistan Province",
      "original_text_name": "Islamic State – Pakistan Province",
      "aliases": [
        "ISPP"
      ],
      "context": "IS affiliate in Pakistan, split from ISIS-K.",
      "time_period": "2019-present",
      "source_url": "https://en.wikipedia.org/w/index.php?title=Islamic_State&oldid=1359049369"
    },
    {
      "standard_name": "Islamic State – Philippines Province",
      "original_text_name": "Islamic State – Philippines Province",
      "aliases": [
        "ISPP"
      ],
      "context": "IS affiliate in Philippines, emerged from Maute Group, BIFF, and AKP.",
      "time_period": "2016-present",
      "source_url": "https://en.wikipedia.org/w/index.php?title=Islamic_State&oldid=1359049369"
    },
    {
      "standard_name": "Maute Group",
      "original_text_name": "Maute Group",
      "aliases": [],
      "context": "Local jihadist group in Philippines that merged into IS Philippines Province.",
      "time_period": null,
      "source_url": "https://en.wikipedia.org/w/index.php?title=Islamic_State&oldid=1359049369"
    },
    {
      "standard_name": "Bangsamoro Islamic Freedom Fighters",
      "original_text_name": "Bangsamoro Islamic Freedom Fighters",
      "aliases": [
        "BIFF"
      ],
      "context": "Local jihadist group in Philippines that merged into IS Philippines Province.",
      "time_period": null,
      "source_url": "https://en.wikipedia.org/w/index.php?title=Islamic_State&oldid=1359049369"
    },
    {
      "standard_name": "Ansar Khalifa Philippines",
      "original_text_name": "Ansar Khalifa Philippines",
      "aliases": [
        "AKP"
      ],
      "context": "Local jihadist group in Philippines that merged into IS Philippines Province.",
      "time_period": null,
      "source_url": "https://en.wikipedia.org/w/index.php?title=Islamic_State&oldid=1359049369"
    },
    {
      "standard_name": "Islamic State – Turkey Province",
      "original_text_name": "Islamic State – Turkey Province",
      "aliases": [
        "IS-TP"
      ],
      "context": "IS affiliate in Turkey.",
      "time_period": "2019-present",
      "source_url": "https://en.wikipedia.org/w/index.php?title=Islamic_State&oldid=1359049369"
    },
    {
      "standard_name": "Islamic State",
      "original_text_name": "Islamic State",
      "aliases": [
        "IS",
        "ISIL",
        "ISIS",
        "Daesh",
        "Islamic State of Iraq and the Levant",
        "Islamic State of Iraq and Syria"
      ],
      "context": "Transnational Salafi jihadist militant organisation and unrecognised quasi-state that controlled territory in Iraq and Syria from 2013 to 2019.",
      "time_period": "2004-present",
      "source_url": "https://en.wikipedia.org/w/index.php?title=Islamic_State&oldid=1359049369"
    },
    {
      "standard_name": "Al-Qaeda",
      "original_text_name": "al-Qaeda",
      "aliases": [],
      "context": "Jihadist militant organization founded by Osama bin Laden, designated as a terrorist group by the UN.",
      "time_period": null,
      "source_url": "https://en.wikipedia.org/w/index.php?title=Islamic_State&oldid=1359049369"
    },
    {
      "standard_name": "Al-Nusra Front",
      "original_text_name": "al-Nusra Front",
      "aliases": [
        "al-Nusra"
      ],
      "context": "Al-Qaeda affiliate in Syria, also known as Jabhat al-Nusra.",
      "time_period": null,
      "source_url": "https://en.wikipedia.org/w/index.php?title=Islamic_State&oldid=1359049369"
    },
    {
      "standard_name": "Jaysh al-Islam",
      "original_text_name": "Jaysh al-Islam",
      "aliases": [],
      "context": "A group within the Islamic Front, a Syrian rebel coalition.",
      "time_period": null,
      "source_url": "https://en.wikipedia.org/w/index.php?title=Islamic_State&oldid=1359049369"
    },
    {
      "standard_name": "Islamic Front",
      "original_text_name": "Islamic Front",
      "aliases": [],
      "context": "A coalition of Syrian rebel groups.",
      "time_period": null,
      "source_url": "https://en.wikipedia.org/w/index.php?title=Islamic_State&oldid=1359049369"
    },
    {
      "standard_name": "Islamic State",
      "original_text_name": "Islamic State",
      "aliases": [
        "IS",
        "Islamic State of Iraq and the Levant",
        "ISIL",
        "Islamic State of Iraq and Syria",
        "ISIS",
        "Daesh"
      ],
      "context": "Transnational Salafi jihadist militant organisation and unrecognised quasi-state that controlled territory in Iraq and Syria from 2013 to 2019.",
      "time_period": "2004-present",
      "source_url": "https://en.wikipedia.org/w/index.php?title=Islamic_State&oldid=1359049369"
    },
    {
      "standard_name": "Al-Qaeda",
      "original_text_name": "al-Qaeda",
      "aliases": [],
      "context": "Global militant Islamist organization founded by Osama bin Laden.",
      "time_period": null,
      "source_url": "https://en.wikipedia.org/w/index.php?title=Islamic_State&oldid=1359049369"
    },
    {
      "standard_name": "Al-Nusra Front",
      "original_text_name": "al-Nusra Front",
      "aliases": [],
      "context": "Branch of al-Qaeda operating in Syria.",
      "time_period": null,
      "source_url": "https://en.wikipedia.org/w/index.php?title=Islamic_State&oldid=1359049369"
    },
    {
      "standard_name": "Taliban",
      "original_text_name": "Taliban",
      "aliases": [],
      "context": "Islamist militant group that ruled Afghanistan and banned association with IS's Khorasan Province branch in 2022.",
      "time_period": null,
      "source_url": "https://en.wikipedia.org/w/index.php?title=Islamic_State&oldid=1359049369"
    },
    {
      "standard_name": "Islamic State – Khorasan Province",
      "original_text_name": "Khorasan Province branch of IS",
      "aliases": [
        "IS-KP"
      ],
      "context": "Regional branch of Islamic State operating in Afghanistan and Pakistan.",
      "time_period": null,
      "source_url": "https://en.wikipedia.org/w/index.php?title=Islamic_State&oldid=1359049369"
    },
    {
      "standard_name": "Al-Qaeda in the Arabian Peninsula",
      "original_text_name": "Al-Qaeda in the Arabian Peninsula",
      "aliases": [
        "AQAP"
      ],
      "context": "Militant group based in Yemen and Saudi Arabia.",
      "time_period": null,
      "source_url": "https://en.wikipedia.org/w/index.php?title=Islamic_State&oldid=1359049369"
    },
    {
      "standard_name": "Al-Qaeda in the Islamic Maghreb",
      "original_text_name": "Al-Qaeda in the Islamic Maghreb",
      "aliases": [
        "AQIM"
      ],
      "context": "Militant group based in the Maghreb region.",
      "time_period": null,
      "source_url": "https://en.wikipedia.org/w/index.php?title=Islamic_State&oldid=1359049369"
    },
    {
      "standard_name": "Al-Shabaab",
      "original_text_name": "Al-Shabaab",
      "aliases": [],
      "context": "Islamist militant group based in Somalia.",
      "time_period": null,
      "source_url": "https://en.wikipedia.org/w/index.php?title=Islamic_State&oldid=1359049369"
    },
    {
      "standard_name": "Hamas",
      "original_text_name": "Hamas",
      "aliases": [],
      "context": "Palestinian Sunni-Islamist militant group governing the Gaza Strip.",
      "time_period": null,
      "source_url": "https://en.wikipedia.org/w/index.php?title=Islamic_State&oldid=1359049369"
    },
    {
      "standard_name": "Hezbollah",
      "original_text_name": "Hezbollah",
      "aliases": [],
      "context": "Lebanese Shia Islamist political party and militant group.",
      "time_period": null,
      "source_url": "https://en.wikipedia.org/w/index.php?title=Islamic_State&oldid=1359049369"
    },
    {
      "standard_name": "Houthis",
      "original_text_name": "Houthis",
      "aliases": [],
      "context": "Yemeni Shia Islamist rebel group.",
      "time_period": null,
      "source_url": "https://en.wikipedia.org/w/index.php?title=Islamic_State&oldid=1359049369"
    },
    {
      "standard_name": "Kurdistan Workers' Party",
      "original_text_name": "Kurdistan Workers' Party",
      "aliases": [
        "PKK"
      ],
      "context": "Kurdish militant group operating in Turkey, Iraq, and Syria.",
      "time_period": null,
      "source_url": "https://en.wikipedia.org/w/index.php?title=Islamic_State&oldid=1359049369"
    },
    {
      "standard_name": "Syrian Democratic Forces",
      "original_text_name": "Syrian Democratic Forces",
      "aliases": [
        "SDF"
      ],
      "context": "Kurdish-led alliance fighting IS in Syria.",
      "time_period": null,
      "source_url": "https://en.wikipedia.org/w/index.php?title=Islamic_State&oldid=1359049369"
    },
    {
      "standard_name": "Nineveh Plain Protection Units",
      "original_text_name": "Nineveh Plain Protection Units",
      "aliases": [],
      "context": "Assyrian Christian militia in the Nineveh Plains, Northern Iraq.",
      "time_period": null,
      "source_url": "https://en.wikipedia.org/w/index.php?title=Islamic_State&oldid=1359049369"
    },
    {
      "standard_name": "Amal Movement",
      "original_text_name": "Amal Movement",
      "aliases": [],
      "context": "Lebanese Shia political party and militia.",
      "time_period": null,
      "source_url": "https://en.wikipedia.org/w/index.php?title=Islamic_State&oldid=1359049369"
    },
    {
      "standard_name": "Syrian Resistance",
      "original_text_name": "Syrian Resistance",
      "aliases": [
        "Suqur al-Furat"
      ],
      "context": "Syrian militia group.",
      "time_period": null,
      "source_url": "https://en.wikipedia.org/w/index.php?title=Islamic_State&oldid=1359049369"
    },
    {
      "standard_name": "Liwa al-Quds",
      "original_text_name": "Liwa al-Quds",
      "aliases": [],
      "context": "Palestinian militia fighting in Syria.",
      "time_period": null,
      "source_url": "https://en.wikipedia.org/w/index.php?title=Islamic_State&oldid=1359049369"
    },
    {
      "standard_name": "Liwa Abu al-Fadhal al-Abbas",
      "original_text_name": "Liwa Abu al-Fadhal al-Abbas",
      "aliases": [],
      "context": "Shia militia fighting in Syria.",
      "time_period": null,
      "source_url": "https://en.wikipedia.org/w/index.php?title=Islamic_State&oldid=1359049369"
    },
    {
      "standard_name": "Abu al-Fadl al-Abbas Forces",
      "original_text_name": "Abu al-Fadl al-Abbas Forces",
      "aliases": [],
      "context": "Shia militia group.",
      "time_period": null,
      "source_url": "https://en.wikipedia.org/w/index.php?title=Islamic_State&oldid=1359049369"
    },
    {
      "standard_name": "Islamic Jihad Movement in Palestine",
      "original_text_name": "Islamic Jihad Movement in Palestine",
      "aliases": [],
      "context": "Palestinian Islamist militant group.",
      "time_period": null,
      "source_url": "https://en.wikipedia.org/w/index.php?title=Islamic_State&oldid=1359049369"
    },
    {
      "standard_name": "Arab Nationalist Guard",
      "original_text_name": "Arab Nationalist Guard",
      "aliases": [],
      "context": "Syrian militia group.",
      "time_period": null,
      "source_url": "https://en.wikipedia.org/w/index.php?title=Islamic_State&oldid=1359049369"
    },
    {
      "standard_name": "Popular Front for the Liberation of Palestine – General Command",
      "original_text_name": "Popular Front for the Liberation of Palestine – General Command",
      "aliases": [],
      "context": "Palestinian militant group.",
      "time_period": null,
      "source_url": "https://en.wikipedia.org/w/index.php?title=Islamic_State&oldid=1359049369"
    },
    {
      "standard_name": "Syrian Revolutionary Command Council",
      "original_text_name": "Syrian Revolutionary Command Council",
      "aliases": [],
      "context": "Syrian opposition coalition.",
      "time_period": null,
      "source_url": "https://en.wikipedia.org/w/index.php?title=Islamic_State&oldid=1359049369"
    },
    {
      "standard_name": "Mujahideen Shura Council (Syria)",
      "original_text_name": "Mujahideen Shura Council (Syria)",
      "aliases": [],
      "context": "Syrian Islamist rebel alliance.",
      "time_period": null,
      "source_url": "https://en.wikipedia.org/w/index.php?title=Islamic_State&oldid=1359049369"
    },
    {
      "standard_name": "Unified Military Command of Eastern Ghouta",
      "original_text_name": "Unified Military Command of Eastern Ghouta",
      "aliases": [],
      "context": "Syrian rebel coalition in Eastern Ghouta.",
      "time_period": null,
      "source_url": "https://en.wikipedia.org/w/index.php?title=Islamic_State&oldid=1359049369"
    },
    {
      "standard_name": "Fatah Halab",
      "original_text_name": "Fatah Halab",
      "aliases": [],
      "context": "Syrian rebel coalition in Aleppo.",
      "time_period": null,
      "source_url": "https://en.wikipedia.org/w/index.php?title=Islamic_State&oldid=1359049369"
    },
    {
      "standard_name": "Mare' Operations Room",
      "original_text_name": "Mare' Operations Room",
      "aliases": [],
      "context": "Syrian rebel coalition.",
      "time_period": null,
      "source_url": "https://en.wikipedia.org/w/index.php?title=Islamic_State&oldid=1359049369"
    },
    {
      "standard_name": "Golan Regiment",
      "original_text_name": "Golan Regiment",
      "aliases": [],
      "context": "Syrian rebel group.",
      "time_period": null,
      "source_url": "https://en.wikipedia.org/w/index.php?title=Islamic_State&oldid=1359049369"
    },
    {
      "standard_name": "Mukhtar Army",
      "original_text_name": "Mukhtar Army",
      "aliases": [],
      "context": "Iraqi Shia militia.",
      "time_period": null,
      "source_url": "https://en.wikipedia.org/w/index.php?title=Islamic_State&oldid=1359049369"
    }
  ],
  "edges": [
    {
      "source": "Islamic State",
      "target": "Al-Qaeda",
      "evidence_quote": "the organisation (primarily under the Islamic State of Iraq name) affiliated itself with al-Qaeda in Iraq and fought alongside them during the 2003–2006 phase of the Iraqi insurgency",
      "context": "Islamic State (as ISI) affiliated with al-Qaeda in Iraq and fought alongside them.",
      "relationship": "cooperation",
      "time_period": "2003–2006",
      "source_url": "https://en.wikipedia.org/w/index.php?title=Islamic_State&oldid=1359049369"
    },
    {
      "source": "Islamic State",
      "target": "Al-Qaeda",
      "evidence_quote": "3 February 2014 : Beginning of Al-Qaeda–Islamic State conflict",
      "context": "Al-Qaeda and Islamic State entered open conflict starting February 2014.",
      "relationship": "conflict",
      "time_period": "2014",
      "source_url": "https://en.wikipedia.org/w/index.php?title=Islamic_State&oldid=1359049369"
    },
    {
      "source": "Islamic State",
      "target": "Al-Nusra Front",
      "evidence_quote": "Opponents: ... Al-Nusra Front",
      "context": "Al-Nusra Front is listed as an opponent of Islamic State.",
      "relationship": "conflict",
      "time_period": null,
      "source_url": "https://en.wikipedia.org/w/index.php?title=Islamic_State&oldid=1359049369"
    },
    {
      "source": "Islamic State",
      "target": "Hay'at Tahrir al-Sham",
      "evidence_quote": "Opponents: ... Hay'at Tahrir al-Sham",
      "context": "Hay'at Tahrir al-Sham is listed as an opponent of Islamic State.",
      "relationship": "conflict",
      "time_period": null,
      "source_url": "https://en.wikipedia.org/w/index.php?title=Islamic_State&oldid=1359049369"
    },
    {
      "source": "Islamic State",
      "target": "Hamas",
      "evidence_quote": "IS regards the Palestinian Sunni group Hamas as apostates who have no legitimate authority to lead jihad and see fighting Hamas as the first step towards confrontation by IS with Israel.",
      "context": "Islamic State regards Hamas as apostates and considers them opponents.",
      "relationship": "conflict",
      "time_period": null,
      "source_url": "https://en.wikipedia.org/w/index.php?title=Islamic_State&oldid=1359049369"
    },
    {
      "source": "Islamic State",
      "target": "Hezbollah",
      "evidence_quote": "Opponents: ... Hezbollah",
      "context": "Hezbollah is listed as an opponent of Islamic State.",
      "relationship": "conflict",
      "time_period": null,
      "source_url": "https://en.wikipedia.org/w/index.php?title=Islamic_State&oldid=1359049369"
    },
    {
      "source": "Islamic State",
      "target": "Houthis",
      "evidence_quote": "Opponents: ... Houthis",
      "context": "Houthis are listed as an opponent of Islamic State.",
      "relationship": "conflict",
      "time_period": null,
      "source_url": "https://en.wikipedia.org/w/index.php?title=Islamic_State&oldid=1359049369"
    },
    {
      "source": "Islamic State",
      "target": "Free Syrian Army",
      "evidence_quote": "Opponents: ... Free Syrian Army",
      "context": "Free Syrian Army is listed as an opponent of Islamic State.",
      "relationship": "conflict",
      "time_period": null,
      "source_url": "https://en.wikipedia.org/w/index.php?title=Islamic_State&oldid=1359049369"
    },
    {
      "source": "Islamic State",
      "target": "Syrian Democratic Forces",
      "evidence_quote": "After 2015, the Iraqi Armed Forces and the Syrian Democratic Forces pushed back IS",
      "context": "Syrian Democratic Forces fought against Islamic State and pushed it back.",
      "relationship": "conflict",
      "time_period": "after 2015",
      "source_url": "https://en.wikipedia.org/w/index.php?title=Islamic_State&oldid=1359049369"
    },
    {
      "source": "Islamic State",
      "target": "Peshmerga",
      "evidence_quote": "Opponents: ... Peshmerga",
      "context": "Peshmerga is listed as an opponent of Islamic State.",
      "relationship": "conflict",
      "time_period": null,
      "source_url": "https://en.wikipedia.org/w/index.php?title=Islamic_State&oldid=1359049369"
    },
    {
      "source": "Islamic State",
      "target": "Popular Mobilization Units",
      "evidence_quote": "Opponents: ... Popular Mobilization Units",
      "context": "Popular Mobilization Units are listed as opponents of Islamic State.",
      "relationship": "conflict",
      "time_period": null,
      "source_url": "https://en.wikipedia.org/w/index.php?title=Islamic_State&oldid=1359049369"
    },
    {
      "source": "Islamic State",
      "target": "Asa'ib Ahl al-Haq",
      "evidence_quote": "Opponents: ... Asa'ib Ahl al-Haq",
      "context": "Asa'ib Ahl al-Haq is listed as an opponent of Islamic State.",
      "relationship": "conflict",
      "time_period": null,
      "source_url": "https://en.wikipedia.org/w/index.php?title=Islamic_State&oldid=1359049369"
    },
    {
      "source": "Islamic State",
      "target": "Kata'ib Hezbollah",
      "evidence_quote": "Opponents: ... Kata'ib Hezbollah",
      "context": "Kata'ib Hezbollah is listed as an opponent of Islamic State.",
      "relationship": "conflict",
      "time_period": null,
      "source_url": "https://en.wikipedia.org/w/index.php?title=Islamic_State&oldid=1359049369"
    },
    {
      "source": "Islamic State",
      "target": "Harakat Hezbollah al-Nujaba",
      "evidence_quote": "Opponents: ... Harakat Hezbollah al-Nujaba",
      "context": "Harakat Hezbollah al-Nujaba is listed as an opponent of Islamic State.",
      "relationship": "conflict",
      "time_period": null,
      "source_url": "https://en.wikipedia.org/w/index.php?title=Islamic_State&oldid=1359049369"
    },
    {
      "source": "Islamic State",
      "target": "Kata'ib Sayyid al-Shuhada",
      "evidence_quote": "Opponents: ... Kata'ib Sayyid al-Shuhada",
      "context": "Kata'ib Sayyid al-Shuhada is listed as an opponent of Islamic State.",
      "relationship": "conflict",
      "time_period": null,
      "source_url": "https://en.wikipedia.org/w/index.php?title=Islamic_State&oldid=1359049369"
    },
    {
      "source": "Islamic State",
      "target": "Badr Organization",
      "evidence_quote": "Opponents: ... Badr Organization",
      "context": "Badr Organization is listed as an opponent of Islamic State.",
      "relationship": "conflict",
      "time_period": null,
      "source_url": "https://en.wikipedia.org/w/index.php?title=Islamic_State&oldid=1359049369"
    },
    {
      "source": "Islamic State",
      "target": "Ahrar al-Sham",
      "evidence_quote": "Opponents: ... Ahrar al-Sham",
      "context": "Ahrar al-Sham is listed as an opponent of Islamic State.",
      "relationship": "conflict",
      "time_period": null,
      "source_url": "https://en.wikipedia.org/w/index.php?title=Islamic_State&oldid=1359049369"
    },
    {
      "source": "Islamic State",
      "target": "Army of Conquest",
      "evidence_quote": "Opponents: ... Army of Conquest",
      "context": "Army of Conquest is listed as an opponent of Islamic State.",
      "relationship": "conflict",
      "time_period": null,
      "source_url": "https://en.wikipedia.org/w/index.php?title=Islamic_State&oldid=1359049369"
    },
    {
      "source": "Islamic State",
      "target": "Islamic Front",
      "evidence_quote": "Opponents: ... Islamic Front",
      "context": "Islamic Front is listed as an opponent of Islamic State.",
      "relationship": "conflict",
      "time_period": null,
      "source_url": "https://en.wikipedia.org/w/index.php?title=Islamic_State&oldid=1359049369"
    },
    {
      "source": "Islamic State",
      "target": "Ajnad al-Sham Islamic Union",
      "evidence_quote": "Opponents: ... Ajnad al-Sham Islamic Union",
      "context": "Ajnad al-Sham Islamic Union is listed as an opponent of Islamic State.",
      "relationship": "conflict",
      "time_period": null,
      "source_url": "https://en.wikipedia.org/w/index.php?title=Islamic_State&oldid=1359049369"
    },
    {
      "source": "Islamic State",
      "target": "Ba'ath Brigades",
      "evidence_quote": "Opponents: ... Ba'ath Brigades",
      "context": "Ba'ath Brigades are listed as opponents of Islamic State.",
      "relationship": "conflict",
      "time_period": null,
      "source_url": "https://en.wikipedia.org/w/index.php?title=Islamic_State&oldid=1359049369"
    },
    {
      "source": "Islamic State",
      "target": "Syrian National Army",
      "evidence_quote": "Opponents: ... Syrian National Army",
      "context": "Syrian National Army is listed as an opponent of Islamic State.",
      "relationship": "conflict",
      "time_period": null,
      "source_url": "https://en.wikipedia.org/w/index.php?title=Islamic_State&oldid=1359049369"
    },
    {
      "source": "Islamic State",
      "target": "Nineveh Plain Protection Units",
      "evidence_quote": "Opponents: ... Nineveh Plain Protection Units",
      "context": "Nineveh Plain Protection Units are listed as opponents of Islamic State.",
      "relationship": "conflict",
      "time_period": null,
      "source_url": "https://en.wikipedia.org/w/index.php?title=Islamic_State&oldid=1359049369"
    },
    {
      "source": "Islamic State",
      "target": "National Defence Forces",
      "evidence_quote": "Opponents: ... National Defence Forces",
      "context": "National Defence Forces are listed as opponents of Islamic State.",
      "relationship": "conflict",
      "time_period": null,
      "source_url": "https://en.wikipedia.org/w/index.php?title=Islamic_State&oldid=1359049369"
    },
    {
      "source": "Islamic State",
      "target": "Kurdistan Communities Union",
      "evidence_quote": "Opponents: ... Kurdistan Communities Union",
      "context": "Kurdistan Communities Union is listed as an opponent of Islamic State.",
      "relationship": "conflict",
      "time_period": null,
      "source_url": "https://en.wikipedia.org/w/index.php?title=Islamic_State&oldid=1359049369"
    },
    {
      "source": "Islamic State",
      "target": "Libya Shield Force",
      "evidence_quote": "Opponents: ... Libya Shield Force",
      "context": "Libya Shield Force is listed as an opponent of Islamic State.",
      "relationship": "conflict",
      "time_period": null,
      "source_url": "https://en.wikipedia.org/w/index.php?title=Islamic_State&oldid=1359049369"
    },
    {
      "source": "Islamic State",
      "target": "Shura Council of Mujahideen in Derna",
      "evidence_quote": "Opponents: ... Shura Council of Mujahideen in Derna",
      "context": "Shura Council of Mujahideen in Derna is listed as an opponent of Islamic State.",
      "relationship": "conflict",
      "time_period": null,
      "source_url": "https://en.wikipedia.org/w/index.php?title=Islamic_State&oldid=1359049369"
    },
    {
      "source": "Islamic State",
      "target": "Liwa Assad Allah al-Ghalib fi al-Iraq wa al-Sham",
      "evidence_quote": "Opponents: ... Liwa Assad Allah al-Ghalib fi al-Iraq wa al-Sham",
      "context": "Liwa Assad Allah al-Ghalib fi al-Iraq wa al-Sham is listed as an opponent of Islamic State.",
      "relationship": "conflict",
      "time_period": null,
      "source_url": "https://en.wikipedia.org/w/index.php?title=Islamic_State&oldid=1359049369"
    },
    {
      "source": "Islamic State",
      "target": "Jaysh al-Mu'ammal",
      "evidence_quote": "Opponents: ... Jaysh al-Mu'ammal",
      "context": "Jaysh al-Mu'ammal is listed as an opponent of Islamic State.",
      "relationship": "conflict",
      "time_period": null,
      "source_url": "https://en.wikipedia.org/w/index.php?title=Islamic_State&oldid=1359049369"
    },
    {
      "source": "Islamic State",
      "target": "Liwa Fatemiyoun",
      "evidence_quote": "Opponents: ... Liwa Fatemiyoun",
      "context": "Liwa Fatemiyoun is listed as an opponent of Islamic State.",
      "relationship": "conflict",
      "time_period": null,
      "source_url": "https://en.wikipedia.org/w/index.php?title=Islamic_State&oldid=1359049369"
    },
    {
      "source": "Islamic State",
      "target": "Liwa Zainebiyoun",
      "evidence_quote": "Opponents: ... Liwa Zainebiyoun",
      "context": "Liwa Zainebiyoun is listed as an opponent of Islamic State.",
      "relationship": "conflict",
      "time_period": null,
      "source_url": "https://en.wikipedia.org/w/index.php?title=Islamic_State&oldid=1359049369"
    },
    {
      "source": "Islamic State",
      "target": "Husayniyun",
      "evidence_quote": "Opponents: ... Husayniyun/Hüseynçilər",
      "context": "Husayniyun is listed as an opponent of Islamic State.",
      "relationship": "conflict",
      "time_period": null,
      "source_url": "https://en.wikipedia.org/w/index.php?title=Islamic_State&oldid=1359049369"
    },
    {
      "source": "Islamic State",
      "target": "Army of the Men of the Naqshbandi Order",
      "evidence_quote": "Allies: Army of the Men of the Naqshbandi Order (2014–2015)",
      "context": "Army of the Men of the Naqshbandi Order was an ally of Islamic State from 2014 to 2015.",
      "relationship": "cooperation",
      "time_period": "2014–2015",
      "source_url": "https://en.wikipedia.org/w/index.php?title=Islamic_State&oldid=1359049369"
    },
    {
      "source": "Islamic State",
      "target": "General Military Council for Iraqi Revolutionaries",
      "evidence_quote": "Allies: General Military Council for Iraqi Revolutionaries (2014)",
      "context": "General Military Council for Iraqi Revolutionaries was an ally of Islamic State in 2014.",
      "relationship": "cooperation",
      "time_period": "2014",
      "source_url": "https://en.wikipedia.org/w/index.php?title=Islamic_State&oldid=1359049369"
    },
    {
      "source": "Islamic State",
      "target": "Jaish al-Ta'ifa al-Mansurah",
      "evidence_quote": "Originating in the Jaish al-Ta'ifa al-Mansurah founded by Abu Omar al-Baghdadi in 2004",
      "context": "Islamic State originated from Jaish al-Ta'ifa al-Mansurah.",
      "relationship": "other",
      "time_period": "2004",
      "source_url": "https://en.wikipedia.org/w/index.php?title=Islamic_State&oldid=1359049369"
    },
    {
      "source": "Islamic State",
      "target": "Jaish al-Ta'ifa al-Mansurah",
      "evidence_quote": "Originating in the Jaish al-Ta'ifa al-Mansurah founded by Abu Omar al-Baghdadi in 2004, the organisation (primarily under the Islamic State of Iraq name) affiliated itself with al-Qaeda in Iraq and fought alongside them during the 2003–2006 phase of the Iraqi insurgency.",
      "context": "The Islamic State originated from Jaish al-Ta'ifa al-Mansurah, which was its predecessor.",
      "relationship": "other",
      "time_period": "2004",
      "source_url": "https://en.wikipedia.org/w/index.php?title=Islamic_State&oldid=1359049369"
    },
    {
      "source": "Islamic State",
      "target": "Al-Qaeda",
      "evidence_quote": "the organisation (primarily under the Islamic State of Iraq name) affiliated itself with al-Qaeda in Iraq and fought alongside them during the 2003–2006 phase of the Iraqi insurgency.",
      "context": "The Islamic State (as Islamic State of Iraq) was affiliated with al-Qaeda and fought alongside them.",
      "relationship": "cooperation",
      "time_period": "2003-2006",
      "source_url": "https://en.wikipedia.org/w/index.php?title=Islamic_State&oldid=1359049369"
    },
    {
      "source": "Islamic State",
      "target": "Tahrir al-Sham",
      "evidence_quote": "the Islamic State claimed that al-Husseini al-Qurashi was killed in a shootout with Tahrir al-Sham (HTS) forces.",
      "context": "Islamic State and Tahrir al-Sham were in conflict, resulting in the death of an IS leader.",
      "relationship": "conflict",
      "time_period": null,
      "source_url": "https://en.wikipedia.org/w/index.php?title=Islamic_State&oldid=1359049369"
    },
    {
      "source": "Islamic State",
      "target": "Al-Qaeda",
      "evidence_quote": "The financial support from Al Qaeda came after Zarqawi was reluctant to be recruited by bin Laden.",
      "context": "Al-Qaeda provided financial support to JTJ, the precursor to IS.",
      "relationship": "cooperation",
      "time_period": null,
      "source_url": "https://en.wikipedia.org/w/index.php?title=Islamic_State&oldid=1359049369"
    },
    {
      "source": "Islamic State",
      "target": "Al-Qaeda in Iraq",
      "evidence_quote": "the organisation (primarily under the Islamic State of Iraq name) affiliated itself with al-Qaeda in Iraq and fought alongside them during the 2003–2006 phase of the Iraqi insurgency.",
      "context": "Islamic State of Iraq fought alongside al-Qaeda in Iraq during the insurgency.",
      "relationship": "cooperation",
      "time_period": "2003-2006",
      "source_url": "https://en.wikipedia.org/w/index.php?title=Islamic_State&oldid=1359049369"
    },
    {
      "source": "Islamic State",
      "target": "Al-Khansaa Brigade",
      "evidence_quote": "the media wing of IS's all-female Al-Khansaa Brigade",
      "context": "Al-Khansaa Brigade is the all-female media wing of IS.",
      "relationship": "other",
      "time_period": null,
      "source_url": "https://en.wikipedia.org/w/index.php?title=Islamic_State&oldid=1359049369"
    },
    {
      "source": "Islamic State",
      "target": "Islamic State – Central Africa Province",
      "evidence_quote": "Islamic State – Central Africa Province (IS-CAP) first appeared in 2018 and operates in the Democratic Republic of the Congo and Uganda since 2020. It emerged out of the Ugandan Islamist group Allied Democratic Forces (ADF).",
      "context": "IS-CAP is an official affiliate of IS.",
      "relationship": "other",
      "time_period": "2018-present",
      "source_url": "https://en.wikipedia.org/w/index.php?title=Islamic_State&oldid=1359049369"
    },
    {
      "source": "Islamic State – Central Africa Province",
      "target": "Allied Democratic Forces",
      "evidence_quote": "It emerged out of the Ugandan Islamist group Allied Democratic Forces (ADF).",
      "context": "IS-CAP emerged from the ADF.",
      "relationship": "other",
      "time_period": null,
      "source_url": "https://en.wikipedia.org/w/index.php?title=Islamic_State&oldid=1359049369"
    },
    {
      "source": "Islamic State",
      "target": "Islamic State – Mozambique Province",
      "evidence_quote": "Islamic State – Mozambique Province (ISMP), formerly part of Islamic State – Central Africa Province (IS-CAP), was formed in 2022.",
      "context": "ISMP is an official affiliate of IS, formerly part of IS-CAP.",
      "relationship": "other",
      "time_period": "2022-present",
      "source_url": "https://en.wikipedia.org/w/index.php?title=Islamic_State&oldid=1359049369"
    },
    {
      "source": "Islamic State – Mozambique Province",
      "target": "Al-Shabaab (Mozambique)",
      "evidence_quote": "It emerged out of the Mozambican Islamist group Al-Shabaab.",
      "context": "ISMP emerged from the Mozambican Al-Shabaab group.",
      "relationship": "other",
      "time_period": null,
      "source_url": "https://en.wikipedia.org/w/index.php?title=Islamic_State&oldid=1359049369"
    },
    {
      "source": "Islamic State",
      "target": "Islamic State – Sahel Province",
      "evidence_quote": "Islamic State – Sahel Province (ISSP), formerly known as Islamic State in the Greater Sahara (IS-GS), operates mainly in Mali, Niger and Burkina Faso.",
      "context": "ISSP is an official affiliate of IS.",
      "relationship": "other",
      "time_period": "2015-present",
      "source_url": "https://en.wikipedia.org/w/index.php?title=Islamic_State&oldid=1359049369"
    },
    {
      "source": "Islamic State – Sahel Province",
      "target": "Islamic State – West Africa Province",
      "evidence_quote": "From March 2019 to 2022, IS-GS was formally part of the Islamic State – West Africa Province (ISWAP); when it was also called \"ISWAP-Greater Sahara\".",
      "context": "IS-GS was formally part of ISWAP from 2019 to 2022.",
      "relationship": "other",
      "time_period": "2019-2022",
      "source_url": "https://en.wikipedia.org/w/index.php?title=Islamic_State&oldid=1359049369"
    },
    {
      "source": "Islamic State",
      "target": "Islamic State – West Africa Province",
      "evidence_quote": "Islamic State – West Africa Province (ISWAP) is primarily active in the Chad Basin of Niger, Nigeria, Cameroon and Chad. It emerged in 2015 after a split from Boko Haram.",
      "context": "ISWAP is an official affiliate of IS.",
      "relationship": "other",
      "time_period": "2015-present",
      "source_url": "https://en.wikipedia.org/w/index.php?title=Islamic_State&oldid=1359049369"
    },
    {
      "source": "Islamic State – West Africa Province",
      "target": "Boko Haram",
      "evidence_quote": "It emerged in 2015 after a split from Boko Haram.",
      "context": "ISWAP split from Boko Haram.",
      "relationship": "other",
      "time_period": "2015",
      "source_url": "https://en.wikipedia.org/w/index.php?title=Islamic_State&oldid=1359049369"
    },
    {
      "source": "Islamic State",
      "target": "Islamic State – Somalia Province",
      "evidence_quote": "Islamic State – Somalia Province (ISSP) operates primarily in Puntland in northern Somalia. The group first appeared in 2015 when elements within the Somali Islamist group Al-Shabaab defected and pledged allegiance to IS.",
      "context": "ISSP is an official affiliate of IS, formed by defectors from Al-Shabaab.",
      "relationship": "other",
      "time_period": "2015-present",
      "source_url": "https://en.wikipedia.org/w/index.php?title=Islamic_State&oldid=1359049369"
    },
    {
      "source": "Islamic State – Somalia Province",
      "target": "Al-Shabaab (Somalia)",
      "evidence_quote": "elements within the Somali Islamist group Al-Shabaab defected and pledged allegiance to IS.",
      "context": "ISSP formed from defectors of Al-Shabaab.",
      "relationship": "other",
      "time_period": "2015",
      "source_url": "https://en.wikipedia.org/w/index.php?title=Islamic_State&oldid=1359049369"
    },
    {
      "source": "Islamic State",
      "target": "Islamic State – Azerbaijan Province",
      "evidence_quote": "Islamic State – Azerbaijan Province (IS-AP) emerged in 2019 and operates in Azerbaijan. Its adeherents were previously recruited by both the Islamic State – Caucasus Province (IS-CP) and Islamic State – Khorasan Province (ISIS-K).",
      "context": "IS-AP is an official affiliate of IS.",
      "relationship": "other",
      "time_period": "2019-present",
      "source_url": "https://en.wikipedia.org/w/index.php?title=Islamic_State&oldid=1359049369"
    },
    {
      "source": "Islamic State – Azerbaijan Province",
      "target": "Islamic State – Caucasus Province",
      "evidence_quote": "Its adeherents were previously recruited by both the Islamic State – Caucasus Province (IS-CP) and Islamic State – Khorasan Province (ISIS-K).",
      "context": "IS-AP's adherents were recruited by IS-CP.",
      "relationship": "cooperation",
      "time_period": null,
      "source_url": "https://en.wikipedia.org/w/index.php?title=Islamic_State&oldid=1359049369"
    },
    {
      "source": "Islamic State – Azerbaijan Province",
      "target": "Islamic State – Khorasan Province",
      "evidence_quote": "Its adeherents were previously recruited by both the Islamic State – Caucasus Province (IS-CP) and Islamic State – Khorasan Province (ISIS-K).",
      "context": "IS-AP's adherents were recruited by ISIS-K.",
      "relationship": "cooperation",
      "time_period": null,
      "source_url": "https://en.wikipedia.org/w/index.php?title=Islamic_State&oldid=1359049369"
    },
    {
      "source": "Islamic State",
      "target": "Islamic State – Caucasus Province",
      "evidence_quote": "Islamic State – Caucasus Province (IS-CP) is active in the North Caucasus region of Russia. IS announced the group's formation in 2015.",
      "context": "IS-CP is an official affiliate of IS.",
      "relationship": "other",
      "time_period": "2015-present",
      "source_url": "https://en.wikipedia.org/w/index.php?title=Islamic_State&oldid=1359049369"
    },
    {
      "source": "Islamic State",
      "target": "Islamic State – Khorasan Province",
      "evidence_quote": "Islamic State – Khorasan Province (ISIS-K) emerged in 2015 and operates in Central and South Asia.",
      "context": "ISIS-K is an official affiliate of IS.",
      "relationship": "other",
      "time_period": "2015-present",
      "source_url": "https://en.wikipedia.org/w/index.php?title=Islamic_State&oldid=1359049369"
    },
    {
      "source": "Islamic State",
      "target": "Islamic State – Bengal Province",
      "evidence_quote": "Islamic State – Bengal Province (IS-BP) is active in Bangladesh. The group is an offshoot of the Al-Qaeda affiliated Jamaat-ul-Mujahideen Bangladesh (JMB). It emerged in 2015 and was claimed by IS in 2016.",
      "context": "IS-BP is an official affiliate of IS.",
      "relationship": "other",
      "time_period": "2015-present",
      "source_url": "https://en.wikipedia.org/w/index.php?title=Islamic_State&oldid=1359049369"
    },
    {
      "source": "Islamic State – Bengal Province",
      "target": "Jamaat-ul-Mujahideen Bangladesh",
      "evidence_quote": "The group is an offshoot of the Al-Qaeda affiliated Jamaat-ul-Mujahideen Bangladesh (JMB).",
      "context": "IS-BP is an offshoot of JMB.",
      "relationship": "other",
      "time_period": null,
      "source_url": "https://en.wikipedia.org/w/index.php?title=Islamic_State&oldid=1359049369"
    },
    {
      "source": "Islamic State",
      "target": "Islamic State – Hind Province",
      "evidence_quote": "Islamic State – Hind Province (ISHP) is the Indian branch of IS and operates in Indian Jammu and Kashmir. Its formation was announced in 2019.",
      "context": "ISHP is an official affiliate of IS.",
      "relationship": "other",
      "time_period": "2019-present",
      "source_url": "https://en.wikipedia.org/w/index.php?title=Islamic_State&oldid=1359049369"
    },
    {
      "source": "Islamic State",
      "target": "Islamic State – Pakistan Province",
      "evidence_quote": "Islamic State – Pakistan Province (ISPP) was formed in 2019 as a split from Islamic State – Khorasan Province( ISIS-K).",
      "context": "ISPP is an official affiliate of IS, split from ISIS-K.",
      "relationship": "other",
      "time_period": "2019-present",
      "source_url": "https://en.wikipedia.org/w/index.php?title=Islamic_State&oldid=1359049369"
    },
    {
      "source": "Islamic State – Pakistan Province",
      "target": "Islamic State – Khorasan Province",
      "evidence_quote": "Islamic State – Pakistan Province (ISPP) was formed in 2019 as a split from Islamic State – Khorasan Province( ISIS-K).",
      "context": "ISPP split from ISIS-K.",
      "relationship": "other",
      "time_period": "2019",
      "source_url": "https://en.wikipedia.org/w/index.php?title=Islamic_State&oldid=1359049369"
    },
    {
      "source": "Islamic State",
      "target": "Islamic State – Philippines Province",
      "evidence_quote": "Islamic State – Philippines Province (ISPP) operates in the Philippines, primarily in Mindanao. It emerged in 2016 from local jihadist groups Maute Group, Bangsamoro Islamic Freedom Fighters (BIFF), and Ansar Khalifa Philippines (AKP).",
      "context": "ISPP is an official affiliate of IS.",
      "relationship": "other",
      "time_period": "2016-present",
      "source_url": "https://en.wikipedia.org/w/index.php?title=Islamic_State&oldid=1359049369"
    },
    {
      "source": "Islamic State – Philippines Province",
      "target": "Maute Group",
      "evidence_quote": "It emerged in 2016 from local jihadist groups Maute Group, Bangsamoro Islamic Freedom Fighters (BIFF), and Ansar Khalifa Philippines (AKP).",
      "context": "ISPP emerged from Maute Group.",
      "relationship": "other",
      "time_period": "2016",
      "source_url": "https://en.wikipedia.org/w/index.php?title=Islamic_State&oldid=1359049369"
    },
    {
      "source": "Islamic State – Philippines Province",
      "target": "Bangsamoro Islamic Freedom Fighters",
      "evidence_quote": "It emerged in 2016 from local jihadist groups Maute Group, Bangsamoro Islamic Freedom Fighters (BIFF), and Ansar Khalifa Philippines (AKP).",
      "context": "ISPP emerged from BIFF.",
      "relationship": "other",
      "time_period": "2016",
      "source_url": "https://en.wikipedia.org/w/index.php?title=Islamic_State&oldid=1359049369"
    },
    {
      "source": "Islamic State – Philippines Province",
      "target": "Ansar Khalifa Philippines",
      "evidence_quote": "It emerged in 2016 from local jihadist groups Maute Group, Bangsamoro Islamic Freedom Fighters (BIFF), and Ansar Khalifa Philippines (AKP).",
      "context": "ISPP emerged from AKP.",
      "relationship": "other",
      "time_period": "2016",
      "source_url": "https://en.wikipedia.org/w/index.php?title=Islamic_State&oldid=1359049369"
    },
    {
      "source": "Islamic State",
      "target": "Islamic State – Turkey Province",
      "evidence_quote": "Islamic State – Turkey Province (IS-TP) was formed in 2019 and is active in Turkey.",
      "context": "IS-TP is an official affiliate of IS.",
      "relationship": "other",
      "time_period": "2019-present",
      "source_url": "https://en.wikipedia.org/w/index.php?title=Islamic_State&oldid=1359049369"
    },
    {
      "source": "Islamic State",
      "target": "Al-Qaeda",
      "evidence_quote": "In February 2014, Ayman al-Zawahiri, the leader of Al-Qaeda, announced that his group Al-Qaeda had cut ties with the Islamic State of Iraq and the Levant and denounced ISIL after being unable to reconcile a conflict between them and the al-Qaeda affiliate al-Nusra Front.",
      "context": "Al-Qaeda cut ties with ISIL due to conflict over al-Nusra Front.",
      "relationship": "conflict",
      "time_period": "2014",
      "source_url": "https://en.wikipedia.org/w/index.php?title=Islamic_State&oldid=1359049369"
    },
    {
      "source": "Islamic State",
      "target": "Al-Nusra Front",
      "evidence_quote": "Al-Nusra and ISIL are both hostile towards the Druze. However, while al-Nusra has typically destroyed Druze shrines and pressured them to convert to Sunni Islam, ISIL regards the entire Druze community as a valid target for violence, as it does the Yazidis.",
      "context": "Al-Nusra and ISIL are hostile towards each other, with differing approaches to Druze.",
      "relationship": "conflict",
      "time_period": null,
      "source_url": "https://en.wikipedia.org/w/index.php?title=Islamic_State&oldid=1359049369"
    },
    {
      "source": "Islamic State",
      "target": "Jaysh al-Islam",
      "evidence_quote": "The Jaysh al-Islam group within the Islamic Front criticised ISIL, saying: 'They killed the people of Islam and leave the idol worshippers ... They use the verses talking about the disbelievers and implement it on the Muslims'.",
      "context": "Jaysh al-Islam criticized ISIL for killing Muslims.",
      "relationship": "conflict",
      "time_period": null,
      "source_url": "https://en.wikipedia.org/w/index.php?title=Islamic_State&oldid=1359049369"
    },
    {
      "source": "Islamic State",
      "target": "Al-Qaeda",
      "evidence_quote": "In February 2014, after continued tensions, al-Qaeda publicly disavowed any relations with ISIL.",
      "context": "Al-Qaeda disavowed relations with ISIL in February 2014, indicating a split.",
      "relationship": "conflict",
      "time_period": "February 2014",
      "source_url": "https://en.wikipedia.org/w/index.php?title=Islamic_State&oldid=1359049369"
    },
    {
      "source": "Islamic State",
      "target": "Al-Nusra Front",
      "evidence_quote": "ISIL and al-Nusra Front still cooperate with each other occasionally when they fight against the Syrian government.",
      "context": "ISIL and al-Nusra Front occasionally cooperate against the Syrian government.",
      "relationship": "cooperation",
      "time_period": null,
      "source_url": "https://en.wikipedia.org/w/index.php?title=Islamic_State&oldid=1359049369"
    },
    {
      "source": "Islamic State",
      "target": "Taliban",
      "evidence_quote": "the Taliban banned all Afghans from associating with the local Khorasan Province branch of IS in July 2022, and labelled it a 'false sect'.",
      "context": "Taliban banned association with IS's Khorasan branch, indicating conflict.",
      "relationship": "conflict",
      "time_period": "July 2022",
      "source_url": "https://en.wikipedia.org/w/index.php?title=Islamic_State&oldid=1359049369"
    },
    {
      "source": "Islamic State",
      "target": "Al-Qaeda in the Arabian Peninsula",
      "evidence_quote": "Other non-state opponents: al-Qaeda, al-Nusra Front, Al-Qaeda in the Arabian Peninsula, Al-Qaeda in the Islamic Maghreb, Al-Shabaab, Taliban, Hamas, Hezbollah, Houthis, Kurdistan Workers' Party, Syrian Democratic Forces, ...",
      "context": "IS lists AQAP as a non-state opponent, indicating conflict.",
      "relationship": "conflict",
      "time_period": null,
      "source_url": "https://en.wikipedia.org/w/index.php?title=Islamic_State&oldid=1359049369"
    },
    {
      "source": "Islamic State",
      "target": "Al-Qaeda in the Islamic Maghreb",
      "evidence_quote": "Other non-state opponents: al-Qaeda, al-Nusra Front, Al-Qaeda in the Arabian Peninsula, Al-Qaeda in the Islamic Maghreb, Al-Shabaab, Taliban, Hamas, Hezbollah, Houthis, Kurdistan Workers' Party, Syrian Democratic Forces, ...",
      "context": "IS lists AQIM as a non-state opponent, indicating conflict.",
      "relationship": "conflict",
      "time_period": null,
      "source_url": "https://en.wikipedia.org/w/index.php?title=Islamic_State&oldid=1359049369"
    },
    {
      "source": "Islamic State",
      "target": "Al-Shabaab",
      "evidence_quote": "Other non-state opponents: al-Qaeda, al-Nusra Front, Al-Qaeda in the Arabian Peninsula, Al-Qaeda in the Islamic Maghreb, Al-Shabaab, Taliban, Hamas, Hezbollah, Houthis, Kurdistan Workers' Party, Syrian Democratic Forces, ...",
      "context": "IS lists Al-Shabaab as a non-state opponent, indicating conflict.",
      "relationship": "conflict",
      "time_period": null,
      "source_url": "https://en.wikipedia.org/w/index.php?title=Islamic_State&oldid=1359049369"
    },
    {
      "source": "Islamic State",
      "target": "Hamas",
      "evidence_quote": "Other non-state opponents: al-Qaeda, al-Nusra Front, Al-Qaeda in the Arabian Peninsula, Al-Qaeda in the Islamic Maghreb, Al-Shabaab, Taliban, Hamas, Hezbollah, Houthis, Kurdistan Workers' Party, Syrian Democratic Forces, ...",
      "context": "IS lists Hamas as a non-state opponent, indicating conflict.",
      "relationship": "conflict",
      "time_period": null,
      "source_url": "https://en.wikipedia.org/w/index.php?title=Islamic_State&oldid=1359049369"
    },
    {
      "source": "Islamic State",
      "target": "Hezbollah",
      "evidence_quote": "Other non-state opponents: al-Qaeda, al-Nusra Front, Al-Qaeda in the Arabian Peninsula, Al-Qaeda in the Islamic Maghreb, Al-Shabaab, Taliban, Hamas, Hezbollah, Houthis, Kurdistan Workers' Party, Syrian Democratic Forces, ...",
      "context": "IS lists Hezbollah as a non-state opponent, indicating conflict.",
      "relationship": "conflict",
      "time_period": null,
      "source_url": "https://en.wikipedia.org/w/index.php?title=Islamic_State&oldid=1359049369"
    },
    {
      "source": "Islamic State",
      "target": "Houthis",
      "evidence_quote": "Other non-state opponents: al-Qaeda, al-Nusra Front, Al-Qaeda in the Arabian Peninsula, Al-Qaeda in the Islamic Maghreb, Al-Shabaab, Taliban, Hamas, Hezbollah, Houthis, Kurdistan Workers' Party, Syrian Democratic Forces, ...",
      "context": "IS lists Houthis as a non-state opponent, indicating conflict.",
      "relationship": "conflict",
      "time_period": null,
      "source_url": "https://en.wikipedia.org/w/index.php?title=Islamic_State&oldid=1359049369"
    },
    {
      "source": "Islamic State",
      "target": "Kurdistan Workers' Party",
      "evidence_quote": "Other non-state opponents: al-Qaeda, al-Nusra Front, Al-Qaeda in the Arabian Peninsula, Al-Qaeda in the Islamic Maghreb, Al-Shabaab, Taliban, Hamas, Hezbollah, Houthis, Kurdistan Workers' Party, Syrian Democratic Forces, ...",
      "context": "IS lists PKK as a non-state opponent, indicating conflict.",
      "relationship": "conflict",
      "time_period": null,
      "source_url": "https://en.wikipedia.org/w/index.php?title=Islamic_State&oldid=1359049369"
    },
    {
      "source": "Islamic State",
      "target": "Syrian Democratic Forces",
      "evidence_quote": "Other non-state opponents: al-Qaeda, al-Nusra Front, Al-Qaeda in the Arabian Peninsula, Al-Qaeda in the Islamic Maghreb, Al-Shabaab, Taliban, Hamas, Hezbollah, Houthis, Kurdistan Workers' Party, Syrian Democratic Forces, ...",
      "context": "IS lists SDF as a non-state opponent, indicating conflict.",
      "relationship": "conflict",
      "time_period": null,
      "source_url": "https://en.wikipedia.org/w/index.php?title=Islamic_State&oldid=1359049369"
    },
    {
      "source": "Islamic State",
      "target": "Nineveh Plain Protection Units",
      "evidence_quote": "Other non-state opponents: ... Nineveh Plain Protection Units – an Assyrian Christian militia in the Nineveh Plains in Northern Iraq",
      "context": "IS lists NPU as a non-state opponent, indicating conflict.",
      "relationship": "conflict",
      "time_period": null,
      "source_url": "https://en.wikipedia.org/w/index.php?title=Islamic_State&oldid=1359049369"
    },
    {
      "source": "Islamic State",
      "target": "Amal Movement",
      "evidence_quote": "Other non-state opponents: ... Amal Movement",
      "context": "IS lists Amal Movement as a non-state opponent, indicating conflict.",
      "relationship": "conflict",
      "time_period": null,
      "source_url": "https://en.wikipedia.org/w/index.php?title=Islamic_State&oldid=1359049369"
    },
    {
      "source": "Islamic State",
      "target": "Syrian Resistance",
      "evidence_quote": "Other non-state opponents: ... Syrian Resistance – Suqur al-Furat",
      "context": "IS lists Syrian Resistance as a non-state opponent, indicating conflict.",
      "relationship": "conflict",
      "time_period": null,
      "source_url": "https://en.wikipedia.org/w/index.php?title=Islamic_State&oldid=1359049369"
    },
    {
      "source": "Islamic State",
      "target": "Liwa al-Quds",
      "evidence_quote": "Other non-state opponents: ... Liwa al-Quds",
      "context": "IS lists Liwa al-Quds as a non-state opponent, indicating conflict.",
      "relationship": "conflict",
      "time_period": null,
      "source_url": "https://en.wikipedia.org/w/index.php?title=Islamic_State&oldid=1359049369"
    },
    {
      "source": "Islamic State",
      "target": "Liwa Abu al-Fadhal al-Abbas",
      "evidence_quote": "Other non-state opponents: ... Liwa Abu al-Fadhal al-Abbas",
      "context": "IS lists Liwa Abu al-Fadhal al-Abbas as a non-state opponent, indicating conflict.",
      "relationship": "conflict",
      "time_period": null,
      "source_url": "https://en.wikipedia.org/w/index.php?title=Islamic_State&oldid=1359049369"
    },
    {
      "source": "Islamic State",
      "target": "Abu al-Fadl al-Abbas Forces",
      "evidence_quote": "Other non-state opponents: ... Abu al-Fadl al-Abbas Forces",
      "context": "IS lists Abu al-Fadl al-Abbas Forces as a non-state opponent, indicating conflict.",
      "relationship": "conflict",
      "time_period": null,
      "source_url": "https://en.wikipedia.org/w/index.php?title=Islamic_State&oldid=1359049369"
    },
    {
      "source": "Islamic State",
      "target": "Islamic Jihad Movement in Palestine",
      "evidence_quote": "Other non-state opponents: ... Islamic Jihad Movement in Palestine",
      "context": "IS lists Islamic Jihad Movement in Palestine as a non-state opponent, indicating conflict.",
      "relationship": "conflict",
      "time_period": null,
      "source_url": "https://en.wikipedia.org/w/index.php?title=Islamic_State&oldid=1359049369"
    },
    {
      "source": "Islamic State",
      "target": "Arab Nationalist Guard",
      "evidence_quote": "Other non-state opponents: ... Arab Nationalist Guard",
      "context": "IS lists Arab Nationalist Guard as a non-state opponent, indicating conflict.",
      "relationship": "conflict",
      "time_period": null,
      "source_url": "https://en.wikipedia.org/w/index.php?title=Islamic_State&oldid=1359049369"
    },
    {
      "source": "Islamic State",
      "target": "Popular Front for the Liberation of Palestine – General Command",
      "evidence_quote": "Other non-state opponents: ... Popular Front for the Liberation of Palestine – General Command",
      "context": "IS lists PFLP-GC as a non-state opponent, indicating conflict.",
      "relationship": "conflict",
      "time_period": null,
      "source_url": "https://en.wikipedia.org/w/index.php?title=Islamic_State&oldid=1359049369"
    },
    {
      "source": "Islamic State",
      "target": "Syrian Revolutionary Command Council",
      "evidence_quote": "Other non-state opponents: ... Syrian Revolutionary Command Council",
      "context": "IS lists Syrian Revolutionary Command Council as a non-state opponent, indicating conflict.",
      "relationship": "conflict",
      "time_period": null,
      "source_url": "https://en.wikipedia.org/w/index.php?title=Islamic_State&oldid=1359049369"
    },
    {
      "source": "Islamic State",
      "target": "Mujahideen Shura Council (Syria)",
      "evidence_quote": "Other non-state opponents: ... Mujahideen Shura Council (Syria)",
      "context": "IS lists Mujahideen Shura Council (Syria) as a non-state opponent, indicating conflict.",
      "relationship": "conflict",
      "time_period": null,
      "source_url": "https://en.wikipedia.org/w/index.php?title=Islamic_State&oldid=1359049369"
    },
    {
      "source": "Islamic State",
      "target": "Unified Military Command of Eastern Ghouta",
      "evidence_quote": "Other non-state opponents: ... Unified Military Command of Eastern Ghouta",
      "context": "IS lists Unified Military Command of Eastern Ghouta as a non-state opponent, indicating conflict.",
      "relationship": "conflict",
      "time_period": null,
      "source_url": "https://en.wikipedia.org/w/index.php?title=Islamic_State&oldid=1359049369"
    },
    {
      "source": "Islamic State",
      "target": "Fatah Halab",
      "evidence_quote": "Other non-state opponents: ... Fatah Halab",
      "context": "IS lists Fatah Halab as a non-state opponent, indicating conflict.",
      "relationship": "conflict",
      "time_period": null,
      "source_url": "https://en.wikipedia.org/w/index.php?title=Islamic_State&oldid=1359049369"
    },
    {
      "source": "Islamic State",
      "target": "Mare' Operations Room",
      "evidence_quote": "Other non-state opponents: ... Mare' Operations Room",
      "context": "IS lists Mare' Operations Room as a non-state opponent, indicating conflict.",
      "relationship": "conflict",
      "time_period": null,
      "source_url": "https://en.wikipedia.org/w/index.php?title=Islamic_State&oldid=1359049369"
    },
    {
      "source": "Islamic State",
      "target": "Golan Regiment",
      "evidence_quote": "Other non-state opponents: ... Golan Regiment",
      "context": "IS lists Golan Regiment as a non-state opponent, indicating conflict.",
      "relationship": "conflict",
      "time_period": null,
      "source_url": "https://en.wikipedia.org/w/index.php?title=Islamic_State&oldid=1359049369"
    },
    {
      "source": "Islamic State",
      "target": "Mukhtar Army",
      "evidence_quote": "Other non-state opponents: ... Mukhtar Army",
      "context": "IS lists Mukhtar Army as a non-state opponent, indicating conflict.",
      "relationship": "conflict",
      "time_period": null,
      "source_url": "https://en.wikipedia.org/w/index.php?title=Islamic_State&oldid=1359049369"
    }
  ],
  "source_url": "https://en.wikipedia.org/w/index.php?title=Islamic_State&oldid=1359049369",
  "source_file": "en_Islamic_State"
}